[
  {
    "id": 152034,
    "name": "Abia de la Obispalía",
    "state_id": 5106,
    "state_code": "CU",
    "country_id": 207,
    "country_code": "ES",
    "latitude": "40.01863040",
    "longitude": "-2.39536820",
    "wikiDataId": null
  },
  {
    "id": 32005,
    "name": "Alarcón",
    "state_id": 5106,
    "state_code": "CU",
    "country_id": 207,
    "country_code": "ES",
    "latitude": "39.55000000",
    "longitude": "-2.08333000",
    "wikiDataId": null
  },
  {
    "id": 32018,
    "name": "Albaladejo del Cuende",
    "state_id": 5106,
    "state_code": "CU",
    "country_id": 207,
    "country_code": "ES",
    "latitude": "39.80684000",
    "longitude": "-2.22903000",
    "wikiDataId": null
  },
  {
    "id": 32024,
    "name": "Albalate de las Nogueras",
    "state_id": 5106,
    "state_code": "CU",
    "country_id": 207,
    "country_code": "ES",
    "latitude": "40.36614000",
    "longitude": "-2.27718000",
    "wikiDataId": null
  },
  {
    "id": 32035,
    "name": "Albendea",
    "state_id": 5106,
    "state_code": "CU",
    "country_id": 207,
    "country_code": "ES",
    "latitude": "40.48751000",
    "longitude": "-2.41747000",
    "wikiDataId": null
  },
  {
    "id": 32075,
    "name": "Alcalá de la Vega",
    "state_id": 5106,
    "state_code": "CU",
    "country_id": 207,
    "country_code": "ES",
    "latitude": "40.03333000",
    "longitude": "-1.51667000",
    "wikiDataId": null
  },
  {
    "id": 32085,
    "name": "Alcantud",
    "state_id": 5106,
    "state_code": "CU",
    "country_id": 207,
    "country_code": "ES",
    "latitude": "40.54818000",
    "longitude": "-2.33258000",
    "wikiDataId": null
  },
  {
    "id": 32137,
    "name": "Alcázar del Rey",
    "state_id": 5106,
    "state_code": "CU",
    "country_id": 207,
    "country_code": "ES",
    "latitude": "40.06289000",
    "longitude": "-2.80782000",
    "wikiDataId": null
  },
  {
    "id": 32102,
    "name": "Alcohujate",
    "state_id": 5106,
    "state_code": "CU",
    "country_id": 207,
    "country_code": "ES",
    "latitude": "40.41763000",
    "longitude": "-2.61490000",
    "wikiDataId": null
  },
  {
    "id": 32117,
    "name": "Alconchel de la Estrella",
    "state_id": 5106,
    "state_code": "CU",
    "country_id": 207,
    "country_code": "ES",
    "latitude": "39.71963000",
    "longitude": "-2.57366000",
    "wikiDataId": null
  },
  {
    "id": 32213,
    "name": "Algarra",
    "state_id": 5106,
    "state_code": "CU",
    "country_id": 207,
    "country_code": "ES",
    "latitude": "40.00000000",
    "longitude": "-1.43333000",
    "wikiDataId": null
  },
  {
    "id": 32243,
    "name": "Aliaguilla",
    "state_id": 5106,
    "state_code": "CU",
    "country_id": 207,
    "country_code": "ES",
    "latitude": "39.74143000",
    "longitude": "-1.32567000",
    "wikiDataId": null
  },
  {
    "id": 152038,
    "name": "Almendros",
    "state_id": 5106,
    "state_code": "CU",
    "country_id": 207,
    "country_code": "ES",
    "latitude": "39.87399870",
    "longitude": "-2.86768610",
    "wikiDataId": null
  },
  {
    "id": 32294,
    "name": "Almodóvar del Pinar",
    "state_id": 5106,
    "state_code": "CU",
    "country_id": 207,
    "country_code": "ES",
    "latitude": "39.71667000",
    "longitude": "-1.88333000",
    "wikiDataId": null
  },
  {
    "id": 32304,
    "name": "Almonacid del Marquesado",
    "state_id": 5106,
    "state_code": "CU",
    "country_id": 207,
    "country_code": "ES",
    "latitude": "39.82344000",
    "longitude": "-2.76770000",
    "wikiDataId": null
  },
  {
    "id": 32339,
    "name": "Altarejos",
    "state_id": 5106,
    "state_code": "CU",
    "country_id": 207,
    "country_code": "ES",
    "latitude": "39.91258000",
    "longitude": "-2.35692000",
    "wikiDataId": null
  },
  {
    "id": 32410,
    "name": "Arandilla del Arroyo",
    "state_id": 5106,
    "state_code": "CU",
    "country_id": 207,
    "country_code": "ES",
    "latitude": "40.51056000",
    "longitude": "-2.38355000",
    "wikiDataId": null
  },
  {
    "id": 152076,
    "name": "Arcas del Villar",
    "state_id": 5106,
    "state_code": "CU",
    "country_id": 207,
    "country_code": "ES",
    "latitude": "39.95209090",
    "longitude": "-2.09594290",
    "wikiDataId": null
  },
  {
    "id": 32439,
    "name": "Arcos de la Sierra",
    "state_id": 5106,
    "state_code": "CU",
    "country_id": 207,
    "country_code": "ES",
    "latitude": "40.34664000",
    "longitude": "-2.11310000",
    "wikiDataId": null
  },
  {
    "id": 32475,
    "name": "Arguisuelas",
    "state_id": 5106,
    "state_code": "CU",
    "country_id": 207,
    "country_code": "ES",
    "latitude": "39.83333000",
    "longitude": "-1.81667000",
    "wikiDataId": null
  },
  {
    "id": 32501,
    "name": "Arrancacepas",
    "state_id": 5106,
    "state_code": "CU",
    "country_id": 207,
    "country_code": "ES",
    "latitude": "40.30320000",
    "longitude": "-2.35899000",
    "wikiDataId": null
  },
  {
    "id": 32545,
    "name": "Atalaya del Cañavate",
    "state_id": 5106,
    "state_code": "CU",
    "country_id": 207,
    "country_code": "ES",
    "latitude": "39.51864000",
    "longitude": "-2.25175000",
    "wikiDataId": null
  },
  {
    "id": 32637,
    "name": "Barajas de Melo",
    "state_id": 5106,
    "state_code": "CU",
    "country_id": 207,
    "country_code": "ES",
    "latitude": "40.12340000",
    "longitude": "-2.91675000",
    "wikiDataId": null
  },
  {
    "id": 32655,
    "name": "Barchín del Hoyo",
    "state_id": 5106,
    "state_code": "CU",
    "country_id": 207,
    "country_code": "ES",
    "latitude": "39.66667000",
    "longitude": "-2.06667000",
    "wikiDataId": null
  },
  {
    "id": 32691,
    "name": "Bascuñana de San Pedro",
    "state_id": 5106,
    "state_code": "CU",
    "country_id": 207,
    "country_code": "ES",
    "latitude": "40.21322000",
    "longitude": "-2.22812000",
    "wikiDataId": null
  },
  {
    "id": 32715,
    "name": "Beamud",
    "state_id": 5106,
    "state_code": "CU",
    "country_id": 207,
    "country_code": "ES",
    "latitude": "40.18645000",
    "longitude": "-1.82880000",
    "wikiDataId": null
  },
  {
    "id": 32739,
    "name": "Belinchón",
    "state_id": 5106,
    "state_code": "CU",
    "country_id": 207,
    "country_code": "ES",
    "latitude": "40.04603000",
    "longitude": "-3.05517000",
    "wikiDataId": null
  },
  {
    "id": 32748,
    "name": "Belmonte",
    "state_id": 5106,
    "state_code": "CU",
    "country_id": 207,
    "country_code": "ES",
    "latitude": "39.55746000",
    "longitude": "-2.70461000",
    "wikiDataId": null
  },
  {
    "id": 32751,
    "name": "Belmontejo",
    "state_id": 5106,
    "state_code": "CU",
    "country_id": 207,
    "country_code": "ES",
    "latitude": "39.82212000",
    "longitude": "-2.34467000",
    "wikiDataId": null
  },
  {
    "id": 32881,
    "name": "Beteta",
    "state_id": 5106,
    "state_code": "CU",
    "country_id": 207,
    "country_code": "ES",
    "latitude": "40.57191000",
    "longitude": "-2.07588000",
    "wikiDataId": null
  },
  {
    "id": 32947,
    "name": "Boniches",
    "state_id": 5106,
    "state_code": "CU",
    "country_id": 207,
    "country_code": "ES",
    "latitude": "39.98333000",
    "longitude": "-1.61667000",
    "wikiDataId": null
  },
  {
    "id": 32998,
    "name": "Buciegas",
    "state_id": 5106,
    "state_code": "CU",
    "country_id": 207,
    "country_code": "ES",
    "latitude": "40.33622000",
    "longitude": "-2.46250000",
    "wikiDataId": null
  },
  {
    "id": 33000,
    "name": "Buenache de Alarcón",
    "state_id": 5106,
    "state_code": "CU",
    "country_id": 207,
    "country_code": "ES",
    "latitude": "39.65000000",
    "longitude": "-2.16667000",
    "wikiDataId": null
  },
  {
    "id": 152039,
    "name": "Buenache de la Sierra",
    "state_id": 5106,
    "state_code": "CU",
    "country_id": 207,
    "country_code": "ES",
    "latitude": "40.13476280",
    "longitude": "-2.00130630",
    "wikiDataId": null
  },
  {
    "id": 33006,
    "name": "Buendía",
    "state_id": 5106,
    "state_code": "CU",
    "country_id": 207,
    "country_code": "ES",
    "latitude": "40.36643000",
    "longitude": "-2.75645000",
    "wikiDataId": null
  },
  {
    "id": 33186,
    "name": "Campillo de Altobuey",
    "state_id": 5106,
    "state_code": "CU",
    "country_id": 207,
    "country_code": "ES",
    "latitude": "39.60000000",
    "longitude": "-1.80000000",
    "wikiDataId": null
  },
  {
    "id": 33196,
    "name": "Campillos-Paravientos",
    "state_id": 5106,
    "state_code": "CU",
    "country_id": 207,
    "country_code": "ES",
    "latitude": "39.98333000",
    "longitude": "-1.55000000",
    "wikiDataId": null
  },
  {
    "id": 33197,
    "name": "Campillos-Sierra",
    "state_id": 5106,
    "state_code": "CU",
    "country_id": 207,
    "country_code": "ES",
    "latitude": "40.10000000",
    "longitude": "-1.70000000",
    "wikiDataId": null
  },
  {
    "id": 152072,
    "name": "Campos del Paraíso",
    "state_id": 5106,
    "state_code": "CU",
    "country_id": 207,
    "country_code": "ES",
    "latitude": "40.01103370",
    "longitude": "-2.71827280",
    "wikiDataId": null
  },
  {
    "id": 33530,
    "name": "Cañada del Hoyo",
    "state_id": 5106,
    "state_code": "CU",
    "country_id": 207,
    "country_code": "ES",
    "latitude": "39.96667000",
    "longitude": "-1.90000000",
    "wikiDataId": null
  },
  {
    "id": 152040,
    "name": "Cañada Juncosa",
    "state_id": 5106,
    "state_code": "CU",
    "country_id": 207,
    "country_code": "ES",
    "latitude": "39.54942200",
    "longitude": "-2.25011640",
    "wikiDataId": null
  },
  {
    "id": 33221,
    "name": "Canalejas del Arroyo",
    "state_id": 5106,
    "state_code": "CU",
    "country_id": 207,
    "country_code": "ES",
    "latitude": "40.36850000",
    "longitude": "-2.49408000",
    "wikiDataId": null
  },
  {
    "id": 33532,
    "name": "Cañamares",
    "state_id": 5106,
    "state_code": "CU",
    "country_id": 207,
    "country_code": "ES",
    "latitude": "40.45203000",
    "longitude": "-2.23983000",
    "wikiDataId": null
  },
  {
    "id": 33537,
    "name": "Cañaveras",
    "state_id": 5106,
    "state_code": "CU",
    "country_id": 207,
    "country_code": "ES",
    "latitude": "40.35994000",
    "longitude": "-2.39611000",
    "wikiDataId": null
  },
  {
    "id": 33538,
    "name": "Cañaveruelas",
    "state_id": 5106,
    "state_code": "CU",
    "country_id": 207,
    "country_code": "ES",
    "latitude": "40.40024000",
    "longitude": "-2.63719000",
    "wikiDataId": null
  },
  {
    "id": 33539,
    "name": "Cañete",
    "state_id": 5106,
    "state_code": "CU",
    "country_id": 207,
    "country_code": "ES",
    "latitude": "40.05000000",
    "longitude": "-1.65000000",
    "wikiDataId": null
  },
  {
    "id": 33545,
    "name": "Cañizares",
    "state_id": 5106,
    "state_code": "CU",
    "country_id": 207,
    "country_code": "ES",
    "latitude": "40.51870000",
    "longitude": "-2.19201000",
    "wikiDataId": null
  },
  {
    "id": 33286,
    "name": "Carboneras de Guadazaón",
    "state_id": 5106,
    "state_code": "CU",
    "country_id": 207,
    "country_code": "ES",
    "latitude": "39.88333000",
    "longitude": "-1.80000000",
    "wikiDataId": null
  },
  {
    "id": 33297,
    "name": "Cardenete",
    "state_id": 5106,
    "state_code": "CU",
    "country_id": 207,
    "country_code": "ES",
    "latitude": "39.76667000",
    "longitude": "-1.68333000",
    "wikiDataId": null
  },
  {
    "id": 33321,
    "name": "Carrascosa",
    "state_id": 5106,
    "state_code": "CU",
    "country_id": 207,
    "country_code": "ES",
    "latitude": "40.59092000",
    "longitude": "-2.16305000",
    "wikiDataId": null
  },
  {
    "id": 33323,
    "name": "Carrascosa de Haro",
    "state_id": 5106,
    "state_code": "CU",
    "country_id": 207,
    "country_code": "ES",
    "latitude": "39.59757000",
    "longitude": "-2.54182000",
    "wikiDataId": null
  },
  {
    "id": 33358,
    "name": "Casas de Benítez",
    "state_id": 5106,
    "state_code": "CU",
    "country_id": 207,
    "country_code": "ES",
    "latitude": "39.36667000",
    "longitude": "-2.13333000",
    "wikiDataId": null
  },
  {
    "id": 33362,
    "name": "Casas de Fernando Alonso",
    "state_id": 5106,
    "state_code": "CU",
    "country_id": 207,
    "country_code": "ES",
    "latitude": "39.35065000",
    "longitude": "-2.32402000",
    "wikiDataId": null
  },
  {
    "id": 33363,
    "name": "Casas de Garcimolina",
    "state_id": 5106,
    "state_code": "CU",
    "country_id": 207,
    "country_code": "ES",
    "latitude": "40.00000000",
    "longitude": "-1.41667000",
    "wikiDataId": null
  },
  {
    "id": 33364,
    "name": "Casas de Guijarro",
    "state_id": 5106,
    "state_code": "CU",
    "country_id": 207,
    "country_code": "ES",
    "latitude": "39.35000000",
    "longitude": "-2.16667000",
    "wikiDataId": null
  },
  {
    "id": 33365,
    "name": "Casas de Haro",
    "state_id": 5106,
    "state_code": "CU",
    "country_id": 207,
    "country_code": "ES",
    "latitude": "39.33355000",
    "longitude": "-2.27273000",
    "wikiDataId": null
  },
  {
    "id": 33373,
    "name": "Casas de los Pinos",
    "state_id": 5106,
    "state_code": "CU",
    "country_id": 207,
    "country_code": "ES",
    "latitude": "39.33375000",
    "longitude": "-2.36984000",
    "wikiDataId": null
  },
  {
    "id": 33379,
    "name": "Casasimarro",
    "state_id": 5106,
    "state_code": "CU",
    "country_id": 207,
    "country_code": "ES",
    "latitude": "39.36667000",
    "longitude": "-2.03333000",
    "wikiDataId": null
  },
  {
    "id": 33457,
    "name": "Castillejo de Iniesta",
    "state_id": 5106,
    "state_code": "CU",
    "country_id": 207,
    "country_code": "ES",
    "latitude": "39.53333000",
    "longitude": "-1.76667000",
    "wikiDataId": null
  },
  {
    "id": 33461,
    "name": "Castillejo-Sierra",
    "state_id": 5106,
    "state_code": "CU",
    "country_id": 207,
    "country_code": "ES",
    "latitude": "40.37477000",
    "longitude": "-2.14040000",
    "wikiDataId": null
  },
  {
    "id": 33463,
    "name": "Castillo de Garcimuñoz",
    "state_id": 5106,
    "state_code": "CU",
    "country_id": 207,
    "country_code": "ES",
    "latitude": "39.65928000",
    "longitude": "-2.38030000",
    "wikiDataId": null
  },
  {
    "id": 33466,
    "name": "Castillo-Albaráñez",
    "state_id": 5106,
    "state_code": "CU",
    "country_id": 207,
    "country_code": "ES",
    "latitude": "40.29869000",
    "longitude": "-2.39277000",
    "wikiDataId": null
  },
  {
    "id": 33600,
    "name": "Cervera del Llano",
    "state_id": 5106,
    "state_code": "CU",
    "country_id": 207,
    "country_code": "ES",
    "latitude": "39.78312000",
    "longitude": "-2.42019000",
    "wikiDataId": null
  },
  {
    "id": 33633,
    "name": "Chillarón de Cuenca",
    "state_id": 5106,
    "state_code": "CU",
    "country_id": 207,
    "country_code": "ES",
    "latitude": "40.10539000",
    "longitude": "-2.22181000",
    "wikiDataId": null
  },
  {
    "id": 33651,
    "name": "Chumillas",
    "state_id": 5106,
    "state_code": "CU",
    "country_id": 207,
    "country_code": "ES",
    "latitude": "39.76667000",
    "longitude": "-2.03333000",
    "wikiDataId": null
  },
  {
    "id": 33864,
    "name": "Cuenca",
    "state_id": 5106,
    "state_code": "CU",
    "country_id": 207,
    "country_code": "ES",
    "latitude": "40.06667000",
    "longitude": "-2.13333000",
    "wikiDataId": null
  },
  {
    "id": 33868,
    "name": "Cueva del Hierro",
    "state_id": 5106,
    "state_code": "CU",
    "country_id": 207,
    "country_code": "ES",
    "latitude": "40.58258000",
    "longitude": "-2.03612000",
    "wikiDataId": null
  },
  {
    "id": 152035,
    "name": "El Acebrón",
    "state_id": 5106,
    "state_code": "CU",
    "country_id": 207,
    "country_code": "ES",
    "latitude": "39.90894430",
    "longitude": "-2.98443110",
    "wikiDataId": null
  },
  {
    "id": 152041,
    "name": "El Cañavate",
    "state_id": 5106,
    "state_code": "CU",
    "country_id": 207,
    "country_code": "ES",
    "latitude": "39.54256320",
    "longitude": "-2.30367800",
    "wikiDataId": null
  },
  {
    "id": 152044,
    "name": "El Herrumblar",
    "state_id": 5106,
    "state_code": "CU",
    "country_id": 207,
    "country_code": "ES",
    "latitude": "39.40136630",
    "longitude": "-1.62386700",
    "wikiDataId": null
  },
  {
    "id": 152047,
    "name": "El Hito",
    "state_id": 5106,
    "state_code": "CU",
    "country_id": 207,
    "country_code": "ES",
    "latitude": "39.85902850",
    "longitude": "-2.71516510",
    "wikiDataId": null
  },
  {
    "id": 152052,
    "name": "El Pedernoso",
    "state_id": 5106,
    "state_code": "CU",
    "country_id": 207,
    "country_code": "ES",
    "latitude": "39.48391800",
    "longitude": "-2.74438600",
    "wikiDataId": null
  },
  {
    "id": 152054,
    "name": "El Peral",
    "state_id": 5106,
    "state_code": "CU",
    "country_id": 207,
    "country_code": "ES",
    "latitude": "39.49819470",
    "longitude": "-1.89649220",
    "wikiDataId": null
  },
  {
    "id": 152057,
    "name": "El Picazo",
    "state_id": 5106,
    "state_code": "CU",
    "country_id": 207,
    "country_code": "ES",
    "latitude": "39.44766960",
    "longitude": "-2.09042460",
    "wikiDataId": null
  },
  {
    "id": 152060,
    "name": "El Pozuelo",
    "state_id": 5106,
    "state_code": "CU",
    "country_id": 207,
    "country_code": "ES",
    "latitude": "40.62025320",
    "longitude": "-2.27688930",
    "wikiDataId": null
  },
  {
    "id": 152061,
    "name": "El Provencio",
    "state_id": 5106,
    "state_code": "CU",
    "country_id": 207,
    "country_code": "ES",
    "latitude": "39.37597450",
    "longitude": "-2.57133830",
    "wikiDataId": null
  },
  {
    "id": 152062,
    "name": "El Valle de Altomira",
    "state_id": 5106,
    "state_code": "CU",
    "country_id": 207,
    "country_code": "ES",
    "latitude": "40.22465690",
    "longitude": "-2.76370520",
    "wikiDataId": null
  },
  {
    "id": 34059,
    "name": "Enguídanos",
    "state_id": 5106,
    "state_code": "CU",
    "country_id": 207,
    "country_code": "ES",
    "latitude": "39.66667000",
    "longitude": "-1.60000000",
    "wikiDataId": null
  },
  {
    "id": 34244,
    "name": "Fresneda de Altarejos",
    "state_id": 5106,
    "state_code": "CU",
    "country_id": 207,
    "country_code": "ES",
    "latitude": "39.92577000",
    "longitude": "-2.31498000",
    "wikiDataId": null
  },
  {
    "id": 34246,
    "name": "Fresneda de la Sierra",
    "state_id": 5106,
    "state_code": "CU",
    "country_id": 207,
    "country_code": "ES",
    "latitude": "40.39101000",
    "longitude": "-2.14233000",
    "wikiDataId": null
  },
  {
    "id": 34296,
    "name": "Fuente de Pedro Naharro",
    "state_id": 5106,
    "state_code": "CU",
    "country_id": 207,
    "country_code": "ES",
    "latitude": "39.92438000",
    "longitude": "-3.00916000",
    "wikiDataId": null
  },
  {
    "id": 34321,
    "name": "Fuentelespino de Haro",
    "state_id": 5106,
    "state_code": "CU",
    "country_id": 207,
    "country_code": "ES",
    "latitude": "39.68934000",
    "longitude": "-2.66869000",
    "wikiDataId": null
  },
  {
    "id": 34322,
    "name": "Fuentelespino de Moya",
    "state_id": 5106,
    "state_code": "CU",
    "country_id": 207,
    "country_code": "ES",
    "latitude": "39.91667000",
    "longitude": "-1.46667000",
    "wikiDataId": null
  },
  {
    "id": 152075,
    "name": "Fuentenava de Jábaga",
    "state_id": 5106,
    "state_code": "CU",
    "country_id": 207,
    "country_code": "ES",
    "latitude": "40.08635000",
    "longitude": "-2.26386440",
    "wikiDataId": null
  },
  {
    "id": 34335,
    "name": "Fuentes",
    "state_id": 5106,
    "state_code": "CU",
    "country_id": 207,
    "country_code": "ES",
    "latitude": "39.96667000",
    "longitude": "-2.01667000",
    "wikiDataId": null
  },
  {
    "id": 34363,
    "name": "Fuertescusa",
    "state_id": 5106,
    "state_code": "CU",
    "country_id": 207,
    "country_code": "ES",
    "latitude": "40.47552000",
    "longitude": "-2.17620000",
    "wikiDataId": null
  },
  {
    "id": 34369,
    "name": "Gabaldón",
    "state_id": 5106,
    "state_code": "CU",
    "country_id": 207,
    "country_code": "ES",
    "latitude": "39.61667000",
    "longitude": "-1.93333000",
    "wikiDataId": null
  },
  {
    "id": 34404,
    "name": "Garaballa",
    "state_id": 5106,
    "state_code": "CU",
    "country_id": 207,
    "country_code": "ES",
    "latitude": "39.81667000",
    "longitude": "-1.36667000",
    "wikiDataId": null
  },
  {
    "id": 34431,
    "name": "Gascueña",
    "state_id": 5106,
    "state_code": "CU",
    "country_id": 207,
    "country_code": "ES",
    "latitude": "40.29937000",
    "longitude": "-2.51856000",
    "wikiDataId": null
  },
  {
    "id": 34493,
    "name": "Graja de Campalbo",
    "state_id": 5106,
    "state_code": "CU",
    "country_id": 207,
    "country_code": "ES",
    "latitude": "39.90000000",
    "longitude": "-1.26667000",
    "wikiDataId": null
  },
  {
    "id": 34494,
    "name": "Graja de Iniesta",
    "state_id": 5106,
    "state_code": "CU",
    "country_id": 207,
    "country_code": "ES",
    "latitude": "39.51667000",
    "longitude": "-1.66667000",
    "wikiDataId": null
  },
  {
    "id": 34577,
    "name": "Henarejos",
    "state_id": 5106,
    "state_code": "CU",
    "country_id": 207,
    "country_code": "ES",
    "latitude": "39.86667000",
    "longitude": "-1.48333000",
    "wikiDataId": null
  },
  {
    "id": 152046,
    "name": "Hinojosos Los",
    "state_id": 5106,
    "state_code": "CU",
    "country_id": 207,
    "country_code": "ES",
    "latitude": "39.60336060",
    "longitude": "-2.82655030",
    "wikiDataId": null
  },
  {
    "id": 34636,
    "name": "Honrubia",
    "state_id": 5106,
    "state_code": "CU",
    "country_id": 207,
    "country_code": "ES",
    "latitude": "39.61358000",
    "longitude": "-2.28077000",
    "wikiDataId": null
  },
  {
    "id": 34642,
    "name": "Hontanaya",
    "state_id": 5106,
    "state_code": "CU",
    "country_id": 207,
    "country_code": "ES",
    "latitude": "39.71553000",
    "longitude": "-2.83516000",
    "wikiDataId": null
  },
  {
    "id": 34644,
    "name": "Hontecillas",
    "state_id": 5106,
    "state_code": "CU",
    "country_id": 207,
    "country_code": "ES",
    "latitude": "39.70000000",
    "longitude": "-2.18333000",
    "wikiDataId": null
  },
  {
    "id": 34651,
    "name": "Horcajo de Santiago",
    "state_id": 5106,
    "state_code": "CU",
    "country_id": 207,
    "country_code": "ES",
    "latitude": "39.84221000",
    "longitude": "-2.99724000",
    "wikiDataId": null
  },
  {
    "id": 34709,
    "name": "Huélamo",
    "state_id": 5106,
    "state_code": "CU",
    "country_id": 207,
    "country_code": "ES",
    "latitude": "40.27658000",
    "longitude": "-1.80957000",
    "wikiDataId": null
  },
  {
    "id": 34686,
    "name": "Huelves",
    "state_id": 5106,
    "state_code": "CU",
    "country_id": 207,
    "country_code": "ES",
    "latitude": "40.04282000",
    "longitude": "-2.88444000",
    "wikiDataId": null
  },
  {
    "id": 34714,
    "name": "Huérguina",
    "state_id": 5106,
    "state_code": "CU",
    "country_id": 207,
    "country_code": "ES",
    "latitude": "40.03333000",
    "longitude": "-1.60000000",
    "wikiDataId": null
  },
  {
    "id": 34689,
    "name": "Huerta de la Obispalía",
    "state_id": 5106,
    "state_code": "CU",
    "country_id": 207,
    "country_code": "ES",
    "latitude": "39.98901000",
    "longitude": "-2.47875000",
    "wikiDataId": null
  },
  {
    "id": 34690,
    "name": "Huerta del Marquesado",
    "state_id": 5106,
    "state_code": "CU",
    "country_id": 207,
    "country_code": "ES",
    "latitude": "40.15000000",
    "longitude": "-1.68333000",
    "wikiDataId": null
  },
  {
    "id": 34697,
    "name": "Huete",
    "state_id": 5106,
    "state_code": "CU",
    "country_id": 207,
    "country_code": "ES",
    "latitude": "40.14526000",
    "longitude": "-2.69026000",
    "wikiDataId": null
  },
  {
    "id": 34755,
    "name": "Iniesta",
    "state_id": 5106,
    "state_code": "CU",
    "country_id": 207,
    "country_code": "ES",
    "latitude": "39.43333000",
    "longitude": "-1.75000000",
    "wikiDataId": null
  },
  {
    "id": 152036,
    "name": "La Alberca de Záncara",
    "state_id": 5106,
    "state_code": "CU",
    "country_id": 207,
    "country_code": "ES",
    "latitude": "39.47993430",
    "longitude": "-2.51979320",
    "wikiDataId": null
  },
  {
    "id": 152037,
    "name": "La Almarcha",
    "state_id": 5106,
    "state_code": "CU",
    "country_id": 207,
    "country_code": "ES",
    "latitude": "39.69949610",
    "longitude": "-2.39123620",
    "wikiDataId": null
  },
  {
    "id": 152042,
    "name": "La Cierva",
    "state_id": 5106,
    "state_code": "CU",
    "country_id": 207,
    "country_code": "ES",
    "latitude": "40.06907400",
    "longitude": "-1.85134300",
    "wikiDataId": null
  },
  {
    "id": 152043,
    "name": "La Frontera",
    "state_id": 5106,
    "state_code": "CU",
    "country_id": 207,
    "country_code": "ES",
    "latitude": "40.40180400",
    "longitude": "-2.21690300",
    "wikiDataId": null
  },
  {
    "id": 152045,
    "name": "La Hinojosa",
    "state_id": 5106,
    "state_code": "CU",
    "country_id": 207,
    "country_code": "ES",
    "latitude": "39.72801040",
    "longitude": "-2.41407820",
    "wikiDataId": null
  },
  {
    "id": 152051,
    "name": "La Parra de las Vegas",
    "state_id": 5106,
    "state_code": "CU",
    "country_id": 207,
    "country_code": "ES",
    "latitude": "39.86853440",
    "longitude": "-2.20460800",
    "wikiDataId": null
  },
  {
    "id": 152055,
    "name": "La Peraleja",
    "state_id": 5106,
    "state_code": "CU",
    "country_id": 207,
    "country_code": "ES",
    "latitude": "40.23543290",
    "longitude": "-2.55508540",
    "wikiDataId": null
  },
  {
    "id": 152056,
    "name": "La Pesquera",
    "state_id": 5106,
    "state_code": "CU",
    "country_id": 207,
    "country_code": "ES",
    "latitude": "39.57916620",
    "longitude": "-1.57899940",
    "wikiDataId": null
  },
  {
    "id": 34950,
    "name": "Laguna del Marquesado",
    "state_id": 5106,
    "state_code": "CU",
    "country_id": 207,
    "country_code": "ES",
    "latitude": "40.17749000",
    "longitude": "-1.67167000",
    "wikiDataId": null
  },
  {
    "id": 34951,
    "name": "Lagunaseca",
    "state_id": 5106,
    "state_code": "CU",
    "country_id": 207,
    "country_code": "ES",
    "latitude": "40.53100000",
    "longitude": "-2.01956000",
    "wikiDataId": null
  },
  {
    "id": 34960,
    "name": "Landete",
    "state_id": 5106,
    "state_code": "CU",
    "country_id": 207,
    "country_code": "ES",
    "latitude": "39.90000000",
    "longitude": "-1.36667000",
    "wikiDataId": null
  },
  {
    "id": 152048,
    "name": "Las Majadas",
    "state_id": 5106,
    "state_code": "CU",
    "country_id": 207,
    "country_code": "ES",
    "latitude": "40.31192160",
    "longitude": "-2.00773160",
    "wikiDataId": null
  },
  {
    "id": 152049,
    "name": "Las Mesas",
    "state_id": 5106,
    "state_code": "CU",
    "country_id": 207,
    "country_code": "ES",
    "latitude": "39.38778460",
    "longitude": "-2.76428510",
    "wikiDataId": null
  },
  {
    "id": 152053,
    "name": "Las Pedroñeras",
    "state_id": 5106,
    "state_code": "CU",
    "country_id": 207,
    "country_code": "ES",
    "latitude": "39.44800260",
    "longitude": "-2.67602510",
    "wikiDataId": null
  },
  {
    "id": 152074,
    "name": "Las Valeras",
    "state_id": 5106,
    "state_code": "CU",
    "country_id": 207,
    "country_code": "ES",
    "latitude": "39.78652130",
    "longitude": "-2.15484730",
    "wikiDataId": null
  },
  {
    "id": 35015,
    "name": "Ledaña",
    "state_id": 5106,
    "state_code": "CU",
    "country_id": 207,
    "country_code": "ES",
    "latitude": "39.36667000",
    "longitude": "-1.70000000",
    "wikiDataId": null
  },
  {
    "id": 35020,
    "name": "Leganiel",
    "state_id": 5106,
    "state_code": "CU",
    "country_id": 207,
    "country_code": "ES",
    "latitude": "40.16568000",
    "longitude": "-2.94966000",
    "wikiDataId": null
  },
  {
    "id": 35290,
    "name": "Mariana",
    "state_id": 5106,
    "state_code": "CU",
    "country_id": 207,
    "country_code": "ES",
    "latitude": "40.16717000",
    "longitude": "-2.14601000",
    "wikiDataId": null
  },
  {
    "id": 35320,
    "name": "Masegosa",
    "state_id": 5106,
    "state_code": "CU",
    "country_id": 207,
    "country_code": "ES",
    "latitude": "40.54689000",
    "longitude": "-2.02588000",
    "wikiDataId": null
  },
  {
    "id": 35437,
    "name": "Minglanilla",
    "state_id": 5106,
    "state_code": "CU",
    "country_id": 207,
    "country_code": "ES",
    "latitude": "39.53333000",
    "longitude": "-1.60000000",
    "wikiDataId": null
  },
  {
    "id": 35439,
    "name": "Mira",
    "state_id": 5106,
    "state_code": "CU",
    "country_id": 207,
    "country_code": "ES",
    "latitude": "39.71667000",
    "longitude": "-1.43333000",
    "wikiDataId": null
  },
  {
    "id": 35523,
    "name": "Monreal del Llano",
    "state_id": 5106,
    "state_code": "CU",
    "country_id": 207,
    "country_code": "ES",
    "latitude": "39.56888000",
    "longitude": "-2.76046000",
    "wikiDataId": null
  },
  {
    "id": 35530,
    "name": "Montalbanejo",
    "state_id": 5106,
    "state_code": "CU",
    "country_id": 207,
    "country_code": "ES",
    "latitude": "39.73369000",
    "longitude": "-2.49911000",
    "wikiDataId": null
  },
  {
    "id": 35531,
    "name": "Montalbo",
    "state_id": 5106,
    "state_code": "CU",
    "country_id": 207,
    "country_code": "ES",
    "latitude": "39.87994000",
    "longitude": "-2.67038000",
    "wikiDataId": null
  },
  {
    "id": 35541,
    "name": "Monteagudo de las Salinas",
    "state_id": 5106,
    "state_code": "CU",
    "country_id": 207,
    "country_code": "ES",
    "latitude": "39.80000000",
    "longitude": "-1.90000000",
    "wikiDataId": null
  },
  {
    "id": 35640,
    "name": "Mota de Altarejos",
    "state_id": 5106,
    "state_code": "CU",
    "country_id": 207,
    "country_code": "ES",
    "latitude": "39.88201000",
    "longitude": "-2.30958000",
    "wikiDataId": null
  },
  {
    "id": 35641,
    "name": "Mota del Cuervo",
    "state_id": 5106,
    "state_code": "CU",
    "country_id": 207,
    "country_code": "ES",
    "latitude": "39.50189000",
    "longitude": "-2.86994000",
    "wikiDataId": null
  },
  {
    "id": 35643,
    "name": "Motilla del Palancar",
    "state_id": 5106,
    "state_code": "CU",
    "country_id": 207,
    "country_code": "ES",
    "latitude": "39.56667000",
    "longitude": "-1.88333000",
    "wikiDataId": null
  },
  {
    "id": 35646,
    "name": "Moya",
    "state_id": 5106,
    "state_code": "CU",
    "country_id": 207,
    "country_code": "ES",
    "latitude": "39.95000000",
    "longitude": "-1.36667000",
    "wikiDataId": null
  },
  {
    "id": 35712,
    "name": "Narboneta",
    "state_id": 5106,
    "state_code": "CU",
    "country_id": 207,
    "country_code": "ES",
    "latitude": "39.75000000",
    "longitude": "-1.46667000",
    "wikiDataId": null
  },
  {
    "id": 35890,
    "name": "Olivares de Júcar",
    "state_id": 5106,
    "state_code": "CU",
    "country_id": 207,
    "country_code": "ES",
    "latitude": "39.76101000",
    "longitude": "-2.35589000",
    "wikiDataId": null
  },
  {
    "id": 35896,
    "name": "Olmeda de la Cuesta",
    "state_id": 5106,
    "state_code": "CU",
    "country_id": 207,
    "country_code": "ES",
    "latitude": "40.31088000",
    "longitude": "-2.47592000",
    "wikiDataId": null
  },
  {
    "id": 35897,
    "name": "Olmeda del Rey",
    "state_id": 5106,
    "state_code": "CU",
    "country_id": 207,
    "country_code": "ES",
    "latitude": "39.80000000",
    "longitude": "-2.08333000",
    "wikiDataId": null
  },
  {
    "id": 35898,
    "name": "Olmedilla de Alarcón",
    "state_id": 5106,
    "state_code": "CU",
    "country_id": 207,
    "country_code": "ES",
    "latitude": "39.61667000",
    "longitude": "-2.10000000",
    "wikiDataId": null
  },
  {
    "id": 35899,
    "name": "Olmedilla de Eliz",
    "state_id": 5106,
    "state_code": "CU",
    "country_id": 207,
    "country_code": "ES",
    "latitude": "40.30232000",
    "longitude": "-2.41952000",
    "wikiDataId": null
  },
  {
    "id": 35969,
    "name": "Osa de la Vega",
    "state_id": 5106,
    "state_code": "CU",
    "country_id": 207,
    "country_code": "ES",
    "latitude": "39.65977000",
    "longitude": "-2.75998000",
    "wikiDataId": null
  },
  {
    "id": 36005,
    "name": "Pajarón",
    "state_id": 5106,
    "state_code": "CU",
    "country_id": 207,
    "country_code": "ES",
    "latitude": "39.95000000",
    "longitude": "-1.78333000",
    "wikiDataId": null
  },
  {
    "id": 36004,
    "name": "Pajaroncillo",
    "state_id": 5106,
    "state_code": "CU",
    "country_id": 207,
    "country_code": "ES",
    "latitude": "39.95000000",
    "longitude": "-1.73333000",
    "wikiDataId": null
  },
  {
    "id": 36036,
    "name": "Palomares del Campo",
    "state_id": 5106,
    "state_code": "CU",
    "country_id": 207,
    "country_code": "ES",
    "latitude": "39.94664000",
    "longitude": "-2.59776000",
    "wikiDataId": null
  },
  {
    "id": 152050,
    "name": "Palomera",
    "state_id": 5106,
    "state_code": "CU",
    "country_id": 207,
    "country_code": "ES",
    "latitude": "40.07655610",
    "longitude": "-2.01752420",
    "wikiDataId": null
  },
  {
    "id": 36052,
    "name": "Paracuellos",
    "state_id": 5106,
    "state_code": "CU",
    "country_id": 207,
    "country_code": "ES",
    "latitude": "39.71667000",
    "longitude": "-1.78333000",
    "wikiDataId": null
  },
  {
    "id": 36064,
    "name": "Paredes",
    "state_id": 5106,
    "state_code": "CU",
    "country_id": 207,
    "country_code": "ES",
    "latitude": "40.06578000",
    "longitude": "-2.85400000",
    "wikiDataId": null
  },
  {
    "id": 36193,
    "name": "Pinarejo",
    "state_id": 5106,
    "state_code": "CU",
    "country_id": 207,
    "country_code": "ES",
    "latitude": "39.61639000",
    "longitude": "-2.42592000",
    "wikiDataId": null
  },
  {
    "id": 36196,
    "name": "Pineda de Gigüela",
    "state_id": 5106,
    "state_code": "CU",
    "country_id": 207,
    "country_code": "ES",
    "latitude": "40.08546000",
    "longitude": "-2.54368000",
    "wikiDataId": null
  },
  {
    "id": 36219,
    "name": "Piqueras del Castillo",
    "state_id": 5106,
    "state_code": "CU",
    "country_id": 207,
    "country_code": "ES",
    "latitude": "39.71667000",
    "longitude": "-2.06667000",
    "wikiDataId": null
  },
  {
    "id": 152058,
    "name": "Portalrubio de Guadamejud",
    "state_id": 5106,
    "state_code": "CU",
    "country_id": 207,
    "country_code": "ES",
    "latitude": "40.27265800",
    "longitude": "-2.60342360",
    "wikiDataId": null
  },
  {
    "id": 36290,
    "name": "Portilla",
    "state_id": 5106,
    "state_code": "CU",
    "country_id": 207,
    "country_code": "ES",
    "latitude": "40.28957000",
    "longitude": "-2.08178000",
    "wikiDataId": null
  },
  {
    "id": 152059,
    "name": "Poyatos",
    "state_id": 5106,
    "state_code": "CU",
    "country_id": 207,
    "country_code": "ES",
    "latitude": "40.42270210",
    "longitude": "-2.04997770",
    "wikiDataId": null
  },
  {
    "id": 36321,
    "name": "Pozoamargo",
    "state_id": 5106,
    "state_code": "CU",
    "country_id": 207,
    "country_code": "ES",
    "latitude": "39.36558000",
    "longitude": "-2.19617000",
    "wikiDataId": null
  },
  {
    "id": 152078,
    "name": "Pozorrubielos de la Mancha",
    "state_id": 5106,
    "state_code": "CU",
    "country_id": 207,
    "country_code": "ES",
    "latitude": "39.47901330",
    "longitude": "-2.03711600",
    "wikiDataId": null
  },
  {
    "id": 36326,
    "name": "Pozorrubio",
    "state_id": 5106,
    "state_code": "CU",
    "country_id": 207,
    "country_code": "ES",
    "latitude": "39.81645000",
    "longitude": "-2.94936000",
    "wikiDataId": null
  },
  {
    "id": 36353,
    "name": "Priego",
    "state_id": 5106,
    "state_code": "CU",
    "country_id": 207,
    "country_code": "ES",
    "latitude": "40.44936000",
    "longitude": "-2.31435000",
    "wikiDataId": null
  },
  {
    "id": 36411,
    "name": "Puebla de Almenara",
    "state_id": 5106,
    "state_code": "CU",
    "country_id": 207,
    "country_code": "ES",
    "latitude": "39.78440000",
    "longitude": "-2.81435000",
    "wikiDataId": null
  },
  {
    "id": 36431,
    "name": "Puebla del Salvador",
    "state_id": 5106,
    "state_code": "CU",
    "country_id": 207,
    "country_code": "ES",
    "latitude": "39.56667000",
    "longitude": "-1.66667000",
    "wikiDataId": null
  },
  {
    "id": 36513,
    "name": "Quintanar del Rey",
    "state_id": 5106,
    "state_code": "CU",
    "country_id": 207,
    "country_code": "ES",
    "latitude": "39.33333000",
    "longitude": "-1.93333000",
    "wikiDataId": null
  },
  {
    "id": 36538,
    "name": "Rada de Haro",
    "state_id": 5106,
    "state_code": "CU",
    "country_id": 207,
    "country_code": "ES",
    "latitude": "39.57002000",
    "longitude": "-2.62086000",
    "wikiDataId": null
  },
  {
    "id": 36601,
    "name": "Reíllo",
    "state_id": 5106,
    "state_code": "CU",
    "country_id": 207,
    "country_code": "ES",
    "latitude": "39.90000000",
    "longitude": "-1.86667000",
    "wikiDataId": null
  },
  {
    "id": 36685,
    "name": "Rozalén del Monte",
    "state_id": 5106,
    "state_code": "CU",
    "country_id": 207,
    "country_code": "ES",
    "latitude": "39.99083000",
    "longitude": "-2.80525000",
    "wikiDataId": null
  },
  {
    "id": 36728,
    "name": "Saceda-Trasierra",
    "state_id": 5106,
    "state_code": "CU",
    "country_id": 207,
    "country_code": "ES",
    "latitude": "40.15525000",
    "longitude": "-2.85369000",
    "wikiDataId": null
  },
  {
    "id": 36733,
    "name": "Saelices",
    "state_id": 5106,
    "state_code": "CU",
    "country_id": 207,
    "country_code": "ES",
    "latitude": "39.92061000",
    "longitude": "-2.80502000",
    "wikiDataId": null
  },
  {
    "id": 36766,
    "name": "Salinas del Manzano",
    "state_id": 5106,
    "state_code": "CU",
    "country_id": 207,
    "country_code": "ES",
    "latitude": "40.08333000",
    "longitude": "-1.55000000",
    "wikiDataId": null
  },
  {
    "id": 152063,
    "name": "Salmeroncillos",
    "state_id": 5106,
    "state_code": "CU",
    "country_id": 207,
    "country_code": "ES",
    "latitude": "40.50444200",
    "longitude": "-2.52070740",
    "wikiDataId": null
  },
  {
    "id": 36780,
    "name": "Salvacañete",
    "state_id": 5106,
    "state_code": "CU",
    "country_id": 207,
    "country_code": "ES",
    "latitude": "40.10000000",
    "longitude": "-1.50000000",
    "wikiDataId": null
  },
  {
    "id": 36818,
    "name": "San Clemente",
    "state_id": 5106,
    "state_code": "CU",
    "country_id": 207,
    "country_code": "ES",
    "latitude": "39.40410000",
    "longitude": "-2.42819000",
    "wikiDataId": null
  },
  {
    "id": 36860,
    "name": "San Lorenzo de la Parrilla",
    "state_id": 5106,
    "state_code": "CU",
    "country_id": 207,
    "country_code": "ES",
    "latitude": "39.85129000",
    "longitude": "-2.36079000",
    "wikiDataId": null
  },
  {
    "id": 36863,
    "name": "San Martín de Boniches",
    "state_id": 5106,
    "state_code": "CU",
    "country_id": 207,
    "country_code": "ES",
    "latitude": "39.90000000",
    "longitude": "-1.56667000",
    "wikiDataId": null
  },
  {
    "id": 36902,
    "name": "San Pedro Palmiches",
    "state_id": 5106,
    "state_code": "CU",
    "country_id": 207,
    "country_code": "ES",
    "latitude": "40.42956000",
    "longitude": "-2.40602000",
    "wikiDataId": null
  },
  {
    "id": 37031,
    "name": "Santa Cruz de Moya",
    "state_id": 5106,
    "state_code": "CU",
    "country_id": 207,
    "country_code": "ES",
    "latitude": "39.95000000",
    "longitude": "-1.26667000",
    "wikiDataId": null
  },
  {
    "id": 152064,
    "name": "Santa María de los Llanos",
    "state_id": 5106,
    "state_code": "CU",
    "country_id": 207,
    "country_code": "ES",
    "latitude": "39.49013370",
    "longitude": "-2.80910950",
    "wikiDataId": null
  },
  {
    "id": 37086,
    "name": "Santa María del Campo Rus",
    "state_id": 5106,
    "state_code": "CU",
    "country_id": 207,
    "country_code": "ES",
    "latitude": "39.55942000",
    "longitude": "-2.42306000",
    "wikiDataId": null
  },
  {
    "id": 37090,
    "name": "Santa María del Val",
    "state_id": 5106,
    "state_code": "CU",
    "country_id": 207,
    "country_code": "ES",
    "latitude": "40.50439000",
    "longitude": "-2.04115000",
    "wikiDataId": null
  },
  {
    "id": 37266,
    "name": "Sisante",
    "state_id": 5106,
    "state_code": "CU",
    "country_id": 207,
    "country_code": "ES",
    "latitude": "39.40849000",
    "longitude": "-2.20173000",
    "wikiDataId": null
  },
  {
    "id": 152065,
    "name": "Solera de Gabaldón",
    "state_id": 5106,
    "state_code": "CU",
    "country_id": 207,
    "country_code": "ES",
    "latitude": "39.74913410",
    "longitude": "-1.97653190",
    "wikiDataId": null
  },
  {
    "id": 152079,
    "name": "Sotorribas",
    "state_id": 5106,
    "state_code": "CU",
    "country_id": 207,
    "country_code": "ES",
    "latitude": "40.26752550",
    "longitude": "-2.20399330",
    "wikiDataId": null
  },
  {
    "id": 152066,
    "name": "Talayuelas",
    "state_id": 5106,
    "state_code": "CU",
    "country_id": 207,
    "country_code": "ES",
    "latitude": "39.84955750",
    "longitude": "-1.28308510",
    "wikiDataId": null
  },
  {
    "id": 37372,
    "name": "Tarancón",
    "state_id": 5106,
    "state_code": "CU",
    "country_id": 207,
    "country_code": "ES",
    "latitude": "40.00851000",
    "longitude": "-3.00731000",
    "wikiDataId": null
  },
  {
    "id": 37664,
    "name": "Tébar",
    "state_id": 5106,
    "state_code": "CU",
    "country_id": 207,
    "country_code": "ES",
    "latitude": "39.50000000",
    "longitude": "-2.16667000",
    "wikiDataId": null
  },
  {
    "id": 37395,
    "name": "Tejadillos",
    "state_id": 5106,
    "state_code": "CU",
    "country_id": 207,
    "country_code": "ES",
    "latitude": "40.13333000",
    "longitude": "-1.63333000",
    "wikiDataId": null
  },
  {
    "id": 37426,
    "name": "Tinajas",
    "state_id": 5106,
    "state_code": "CU",
    "country_id": 207,
    "country_code": "ES",
    "latitude": "40.32547000",
    "longitude": "-2.58228000",
    "wikiDataId": null
  },
  {
    "id": 37478,
    "name": "Torralba",
    "state_id": 5106,
    "state_code": "CU",
    "country_id": 207,
    "country_code": "ES",
    "latitude": "40.30253000",
    "longitude": "-2.28546000",
    "wikiDataId": null
  },
  {
    "id": 37537,
    "name": "Torrejoncillo del Rey",
    "state_id": 5106,
    "state_code": "CU",
    "country_id": 207,
    "country_code": "ES",
    "latitude": "40.00840000",
    "longitude": "-2.57107000",
    "wikiDataId": null
  },
  {
    "id": 37595,
    "name": "Torrubia del Campo",
    "state_id": 5106,
    "state_code": "CU",
    "country_id": 207,
    "country_code": "ES",
    "latitude": "39.89749000",
    "longitude": "-2.96133000",
    "wikiDataId": null
  },
  {
    "id": 37596,
    "name": "Torrubia del Castillo",
    "state_id": 5106,
    "state_code": "CU",
    "country_id": 207,
    "country_code": "ES",
    "latitude": "39.65852000",
    "longitude": "-2.31171000",
    "wikiDataId": null
  },
  {
    "id": 152067,
    "name": "Tragacete",
    "state_id": 5106,
    "state_code": "CU",
    "country_id": 207,
    "country_code": "ES",
    "latitude": "40.34960270",
    "longitude": "-1.85073320",
    "wikiDataId": null
  },
  {
    "id": 37631,
    "name": "Tresjuncos",
    "state_id": 5106,
    "state_code": "CU",
    "country_id": 207,
    "country_code": "ES",
    "latitude": "39.70087000",
    "longitude": "-2.75502000",
    "wikiDataId": null
  },
  {
    "id": 37635,
    "name": "Tribaldos",
    "state_id": 5106,
    "state_code": "CU",
    "country_id": 207,
    "country_code": "ES",
    "latitude": "39.97264000",
    "longitude": "-2.89809000",
    "wikiDataId": null
  },
  {
    "id": 37673,
    "name": "Uclés",
    "state_id": 5106,
    "state_code": "CU",
    "country_id": 207,
    "country_code": "ES",
    "latitude": "39.97938000",
    "longitude": "-2.86143000",
    "wikiDataId": null
  },
  {
    "id": 37713,
    "name": "Uña",
    "state_id": 5106,
    "state_code": "CU",
    "country_id": 207,
    "country_code": "ES",
    "latitude": "40.22410000",
    "longitude": "-1.97788000",
    "wikiDataId": null
  },
  {
    "id": 152077,
    "name": "Valdecolmenas Los",
    "state_id": 5106,
    "state_code": "CU",
    "country_id": 207,
    "country_code": "ES",
    "latitude": "40.10878420",
    "longitude": "-2.47030570",
    "wikiDataId": null
  },
  {
    "id": 37768,
    "name": "Valdemeca",
    "state_id": 5106,
    "state_code": "CU",
    "country_id": 207,
    "country_code": "ES",
    "latitude": "40.22367000",
    "longitude": "-1.74358000",
    "wikiDataId": null
  },
  {
    "id": 37773,
    "name": "Valdemorillo de la Sierra",
    "state_id": 5106,
    "state_code": "CU",
    "country_id": 207,
    "country_code": "ES",
    "latitude": "40.03333000",
    "longitude": "-1.78333000",
    "wikiDataId": null
  },
  {
    "id": 37775,
    "name": "Valdemoro-Sierra",
    "state_id": 5106,
    "state_code": "CU",
    "country_id": 207,
    "country_code": "ES",
    "latitude": "40.10000000",
    "longitude": "-1.76667000",
    "wikiDataId": null
  },
  {
    "id": 37779,
    "name": "Valdeolivas",
    "state_id": 5106,
    "state_code": "CU",
    "country_id": 207,
    "country_code": "ES",
    "latitude": "40.50600000",
    "longitude": "-2.44532000",
    "wikiDataId": null
  },
  {
    "id": 152073,
    "name": "Valdetórtola",
    "state_id": 5106,
    "state_code": "CU",
    "country_id": 207,
    "country_code": "ES",
    "latitude": "39.93011190",
    "longitude": "-2.17449930",
    "wikiDataId": null
  },
  {
    "id": 37831,
    "name": "Valhermoso de la Fuente",
    "state_id": 5106,
    "state_code": "CU",
    "country_id": 207,
    "country_code": "ES",
    "latitude": "39.56667000",
    "longitude": "-2.01667000",
    "wikiDataId": null
  },
  {
    "id": 37873,
    "name": "Valsalobre",
    "state_id": 5106,
    "state_code": "CU",
    "country_id": 207,
    "country_code": "ES",
    "latitude": "40.61742000",
    "longitude": "-2.09297000",
    "wikiDataId": null
  },
  {
    "id": 37885,
    "name": "Valverde de Júcar",
    "state_id": 5106,
    "state_code": "CU",
    "country_id": 207,
    "country_code": "ES",
    "latitude": "39.71866000",
    "longitude": "-2.22135000",
    "wikiDataId": null
  },
  {
    "id": 37897,
    "name": "Valverdejo",
    "state_id": 5106,
    "state_code": "CU",
    "country_id": 207,
    "country_code": "ES",
    "latitude": "39.61667000",
    "longitude": "-2.01667000",
    "wikiDataId": null
  },
  {
    "id": 37899,
    "name": "Vara de Rey",
    "state_id": 5106,
    "state_code": "CU",
    "country_id": 207,
    "country_code": "ES",
    "latitude": "39.42595000",
    "longitude": "-2.29404000",
    "wikiDataId": null
  },
  {
    "id": 37914,
    "name": "Vega del Codorno",
    "state_id": 5106,
    "state_code": "CU",
    "country_id": 207,
    "country_code": "ES",
    "latitude": "40.42457000",
    "longitude": "-1.91312000",
    "wikiDataId": null
  },
  {
    "id": 37934,
    "name": "Vellisca",
    "state_id": 5106,
    "state_code": "CU",
    "country_id": 207,
    "country_code": "ES",
    "latitude": "40.12965000",
    "longitude": "-2.81444000",
    "wikiDataId": null
  },
  {
    "id": 38035,
    "name": "Villaconejos de Trabaque",
    "state_id": 5106,
    "state_code": "CU",
    "country_id": 207,
    "country_code": "ES",
    "latitude": "40.40064000",
    "longitude": "-2.31956000",
    "wikiDataId": null
  },
  {
    "id": 152068,
    "name": "Villaescusa de Haro",
    "state_id": 5106,
    "state_code": "CU",
    "country_id": 207,
    "country_code": "ES",
    "latitude": "39.59988760",
    "longitude": "-2.67292020",
    "wikiDataId": null
  },
  {
    "id": 38073,
    "name": "Villagarcía del Llano",
    "state_id": 5106,
    "state_code": "CU",
    "country_id": 207,
    "country_code": "ES",
    "latitude": "39.31667000",
    "longitude": "-1.83333000",
    "wikiDataId": null
  },
  {
    "id": 38098,
    "name": "Villalba de la Sierra",
    "state_id": 5106,
    "state_code": "CU",
    "country_id": 207,
    "country_code": "ES",
    "latitude": "40.23437000",
    "longitude": "-2.08929000",
    "wikiDataId": null
  },
  {
    "id": 38103,
    "name": "Villalba del Rey",
    "state_id": 5106,
    "state_code": "CU",
    "country_id": 207,
    "country_code": "ES",
    "latitude": "40.34653000",
    "longitude": "-2.63902000",
    "wikiDataId": null
  },
  {
    "id": 38113,
    "name": "Villalgordo del Marquesado",
    "state_id": 5106,
    "state_code": "CU",
    "country_id": 207,
    "country_code": "ES",
    "latitude": "39.68245000",
    "longitude": "-2.50885000",
    "wikiDataId": null
  },
  {
    "id": 38121,
    "name": "Villalpardo",
    "state_id": 5106,
    "state_code": "CU",
    "country_id": 207,
    "country_code": "ES",
    "latitude": "39.46667000",
    "longitude": "-1.63333000",
    "wikiDataId": null
  },
  {
    "id": 38144,
    "name": "Villamayor de Santiago",
    "state_id": 5106,
    "state_code": "CU",
    "country_id": 207,
    "country_code": "ES",
    "latitude": "39.73072000",
    "longitude": "-2.92357000",
    "wikiDataId": null
  },
  {
    "id": 152069,
    "name": "Villanueva de Guadamejud",
    "state_id": 5106,
    "state_code": "CU",
    "country_id": 207,
    "country_code": "ES",
    "latitude": "40.22501750",
    "longitude": "-2.50556010",
    "wikiDataId": null
  },
  {
    "id": 38199,
    "name": "Villanueva de la Jara",
    "state_id": 5106,
    "state_code": "CU",
    "country_id": 207,
    "country_code": "ES",
    "latitude": "39.43333000",
    "longitude": "-1.93333000",
    "wikiDataId": null
  },
  {
    "id": 38235,
    "name": "Villar de Cañas",
    "state_id": 5106,
    "state_code": "CU",
    "country_id": 207,
    "country_code": "ES",
    "latitude": "39.77860000",
    "longitude": "-2.56428000",
    "wikiDataId": null
  },
  {
    "id": 38238,
    "name": "Villar de Domingo García",
    "state_id": 5106,
    "state_code": "CU",
    "country_id": 207,
    "country_code": "ES",
    "latitude": "40.23732000",
    "longitude": "-2.29136000",
    "wikiDataId": null
  },
  {
    "id": 38247,
    "name": "Villar de la Encina",
    "state_id": 5106,
    "state_code": "CU",
    "country_id": 207,
    "country_code": "ES",
    "latitude": "39.63725000",
    "longitude": "-2.52155000",
    "wikiDataId": null
  },
  {
    "id": 38241,
    "name": "Villar de Olalla",
    "state_id": 5106,
    "state_code": "CU",
    "country_id": 207,
    "country_code": "ES",
    "latitude": "40.01496000",
    "longitude": "-2.19561000",
    "wikiDataId": null
  },
  {
    "id": 38255,
    "name": "Villar del Humo",
    "state_id": 5106,
    "state_code": "CU",
    "country_id": 207,
    "country_code": "ES",
    "latitude": "39.86667000",
    "longitude": "-1.63333000",
    "wikiDataId": null
  },
  {
    "id": 38256,
    "name": "Villar del Infantado",
    "state_id": 5106,
    "state_code": "CU",
    "country_id": 207,
    "country_code": "ES",
    "latitude": "40.45514000",
    "longitude": "-2.47905000",
    "wikiDataId": null
  },
  {
    "id": 152080,
    "name": "Villar y Velasco",
    "state_id": 5106,
    "state_code": "CU",
    "country_id": 207,
    "country_code": "ES",
    "latitude": "40.14094250",
    "longitude": "-2.40111240",
    "wikiDataId": null
  },
  {
    "id": 38271,
    "name": "Villarejo de Fuentes",
    "state_id": 5106,
    "state_code": "CU",
    "country_id": 207,
    "country_code": "ES",
    "latitude": "39.78809000",
    "longitude": "-2.69680000",
    "wikiDataId": null
  },
  {
    "id": 38274,
    "name": "Villarejo de la Peñuela",
    "state_id": 5106,
    "state_code": "CU",
    "country_id": 207,
    "country_code": "ES",
    "latitude": "40.08745000",
    "longitude": "-2.40996000",
    "wikiDataId": null
  },
  {
    "id": 38277,
    "name": "Villarejo-Periesteban",
    "state_id": 5106,
    "state_code": "CU",
    "country_id": 207,
    "country_code": "ES",
    "latitude": "39.87231000",
    "longitude": "-2.44145000",
    "wikiDataId": null
  },
  {
    "id": 38282,
    "name": "Villares del Saz",
    "state_id": 5106,
    "state_code": "CU",
    "country_id": 207,
    "country_code": "ES",
    "latitude": "39.84109000",
    "longitude": "-2.50427000",
    "wikiDataId": null
  },
  {
    "id": 38304,
    "name": "Villarrubio",
    "state_id": 5106,
    "state_code": "CU",
    "country_id": 207,
    "country_code": "ES",
    "latitude": "39.94511000",
    "longitude": "-2.89431000",
    "wikiDataId": null
  },
  {
    "id": 38306,
    "name": "Villarta",
    "state_id": 5106,
    "state_code": "CU",
    "country_id": 207,
    "country_code": "ES",
    "latitude": "39.45000000",
    "longitude": "-1.65000000",
    "wikiDataId": null
  },
  {
    "id": 152070,
    "name": "Villas de la Ventosa",
    "state_id": 5106,
    "state_code": "CU",
    "country_id": 207,
    "country_code": "ES",
    "latitude": "40.20541470",
    "longitude": "-2.43254220",
    "wikiDataId": null
  },
  {
    "id": 38351,
    "name": "Villaverde y Pasaconsol",
    "state_id": 5106,
    "state_code": "CU",
    "country_id": 207,
    "country_code": "ES",
    "latitude": "39.77099000",
    "longitude": "-2.26552000",
    "wikiDataId": null
  },
  {
    "id": 152071,
    "name": "Víllora",
    "state_id": 5106,
    "state_code": "CU",
    "country_id": 207,
    "country_code": "ES",
    "latitude": "39.75347930",
    "longitude": "-1.58718120",
    "wikiDataId": null
  },
  {
    "id": 38392,
    "name": "Vindel",
    "state_id": 5106,
    "state_code": "CU",
    "country_id": 207,
    "country_code": "ES",
    "latitude": "40.58743000",
    "longitude": "-2.38060000",
    "wikiDataId": null
  },
  {
    "id": 38446,
    "name": "Yémeda",
    "state_id": 5106,
    "state_code": "CU",
    "country_id": 207,
    "country_code": "ES",
    "latitude": "39.76667000",
    "longitude": "-1.71667000",
    "wikiDataId": null
  },
  {
    "id": 38451,
    "name": "Zafra de Záncara",
    "state_id": 5106,
    "state_code": "CU",
    "country_id": 207,
    "country_code": "ES",
    "latitude": "39.89203000",
    "longitude": "-2.55786000",
    "wikiDataId": null
  },
  {
    "id": 38452,
    "name": "Zafrilla",
    "state_id": 5106,
    "state_code": "CU",
    "country_id": 207,
    "country_code": "ES",
    "latitude": "40.20000000",
    "longitude": "-1.61667000",
    "wikiDataId": null
  },
  {
    "id": 38480,
    "name": "Zarza de Tajo",
    "state_id": 5106,
    "state_code": "CU",
    "country_id": 207,
    "country_code": "ES",
    "latitude": "40.01591000",
    "longitude": "-3.12877000",
    "wikiDataId": null
  },
  {
    "id": 38484,
    "name": "Zarzuela",
    "state_id": 5106,
    "state_code": "CU",
    "country_id": 207,
    "country_code": "ES",
    "latitude": "40.25902000",
    "longitude": "-2.11034000",
    "wikiDataId": null
  }
]