[
  {
    "id": 4368,
    "name": "Anenii Noi",
    "country_id": 144,
    "country_code": "MD",
    "state_code": "AN",
    "type": "district",
    "latitude": "46.87956630",
    "longitude": "29.23121750",
    "iso3166_2": "MD-AN",
    "native": "Anenii Noi",
    "timezone": "Europe/Chisinau"
  },
  {
    "id": 4393,
    "name": "Bălți",
    "country_id": 144,
    "country_code": "MD",
    "state_code": "BA",
    "type": "city",
    "latitude": "47.76471360",
    "longitude": "27.91991600",
    "iso3166_2": "MD-BA",
    "native": "Bălți",
    "timezone": "Europe/Chisinau"
  },
  {
    "id": 4379,
    "name": "Basarabeasca",
    "country_id": 144,
    "country_code": "MD",
    "state_code": "BS",
    "type": "district",
    "latitude": "46.39852420",
    "longitude": "28.90220840",
    "iso3166_2": "MD-BS",
    "native": "Basarabeasca",
    "timezone": "Europe/Chisinau"
  },
  {
    "id": 4362,
    "name": "Bender",
    "country_id": 144,
    "country_code": "MD",
    "state_code": "BD",
    "type": "city",
    "latitude": "46.82275510",
    "longitude": "29.46201010",
    "iso3166_2": "MD-BD",
    "native": "Bender",
    "timezone": "Europe/Chisinau"
  },
  {
    "id": 4375,
    "name": "Briceni",
    "country_id": 144,
    "country_code": "MD",
    "state_code": "BR",
    "type": "district",
    "latitude": "48.36320220",
    "longitude": "27.07503980",
    "iso3166_2": "MD-BR",
    "native": "Briceni",
    "timezone": "Europe/Chisinau"
  },
  {
    "id": 4391,
    "name": "Cahul",
    "country_id": 144,
    "country_code": "MD",
    "state_code": "CA",
    "type": "district",
    "latitude": "45.90440870",
    "longitude": "28.19465830",
    "iso3166_2": "MD-CA",
    "native": "Cahul",
    "timezone": "Europe/Chisinau"
  },
  {
    "id": 4366,
    "name": "Călărași",
    "country_id": 144,
    "country_code": "MD",
    "state_code": "CL",
    "type": "district",
    "latitude": "47.27050860",
    "longitude": "28.28756850",
    "iso3166_2": "MD-CL",
    "native": "Călărași",
    "timezone": "Europe/Chisinau"
  },
  {
    "id": 4380,
    "name": "Cantemir",
    "country_id": 144,
    "country_code": "MD",
    "state_code": "CT",
    "type": "district",
    "latitude": "46.27717420",
    "longitude": "28.20096530",
    "iso3166_2": "MD-CT",
    "native": "Cantemir",
    "timezone": "Europe/Chisinau"
  },
  {
    "id": 4365,
    "name": "Căușeni",
    "country_id": 144,
    "country_code": "MD",
    "state_code": "CS",
    "type": "district",
    "latitude": "46.65547150",
    "longitude": "29.40912220",
    "iso3166_2": "MD-CS",
    "native": "Căușeni",
    "timezone": "Europe/Chisinau"
  },
  {
    "id": 4373,
    "name": "Chișinău",
    "country_id": 144,
    "country_code": "MD",
    "state_code": "CU",
    "type": "city",
    "latitude": "47.02451170",
    "longitude": "28.83229230",
    "iso3166_2": "MD-CU",
    "native": "Chișinău",
    "timezone": "Europe/Chisinau"
  },
  {
    "id": 4360,
    "name": "Cimișlia",
    "country_id": 144,
    "country_code": "MD",
    "state_code": "CM",
    "type": "district",
    "latitude": "46.52508510",
    "longitude": "28.77218350",
    "iso3166_2": "MD-CM",
    "native": "Cimișlia",
    "timezone": "Europe/Chisinau"
  },
  {
    "id": 4390,
    "name": "Criuleni",
    "country_id": 144,
    "country_code": "MD",
    "state_code": "CR",
    "type": "district",
    "latitude": "47.21361140",
    "longitude": "29.15575190",
    "iso3166_2": "MD-CR",
    "native": "Criuleni",
    "timezone": "Europe/Chisinau"
  },
  {
    "id": 4384,
    "name": "Dondușeni",
    "country_id": 144,
    "country_code": "MD",
    "state_code": "DO",
    "type": "district",
    "latitude": "48.23383050",
    "longitude": "27.59980870",
    "iso3166_2": "MD-DO",
    "native": "Dondușeni",
    "timezone": "Europe/Chisinau"
  },
  {
    "id": 4392,
    "name": "Drochia",
    "country_id": 144,
    "country_code": "MD",
    "state_code": "DR",
    "type": "district",
    "latitude": "48.11284410",
    "longitude": "27.80954190",
    "iso3166_2": "MD-DR",
    "native": "Drochia",
    "timezone": "Europe/Chisinau"
  },
  {
    "id": 4383,
    "name": "Dubăsari",
    "country_id": 144,
    "country_code": "MD",
    "state_code": "DU",
    "type": "district",
    "latitude": "47.26439420",
    "longitude": "29.15503480",
    "iso3166_2": "MD-DU",
    "native": "Dubăsari",
    "timezone": "Europe/Chisinau"
  },
  {
    "id": 4387,
    "name": "Edineț",
    "country_id": 144,
    "country_code": "MD",
    "state_code": "ED",
    "type": "district",
    "latitude": "48.16789910",
    "longitude": "27.29361430",
    "iso3166_2": "MD-ED",
    "native": "Edineț",
    "timezone": "Europe/Chisinau"
  },
  {
    "id": 4381,
    "name": "Fălești",
    "country_id": 144,
    "country_code": "MD",
    "state_code": "FA",
    "type": "district",
    "latitude": "47.57351410",
    "longitude": "27.70680160",
    "iso3166_2": "MD-FA",
    "native": "Fălești",
    "timezone": "Europe/Chisinau"
  },
  {
    "id": 4370,
    "name": "Florești",
    "country_id": 144,
    "country_code": "MD",
    "state_code": "FL",
    "type": "district",
    "latitude": "47.89914790",
    "longitude": "28.31326120",
    "iso3166_2": "MD-FL",
    "native": "Florești",
    "timezone": "Europe/Chisinau"
  },
  {
    "id": 4385,
    "name": "Gagauzia",
    "country_id": 144,
    "country_code": "MD",
    "state_code": "GA",
    "type": "autonomous territorial unit",
    "latitude": "46.20702040",
    "longitude": "28.76362810",
    "iso3166_2": "MD-GA",
    "native": "Gagauzia",
    "timezone": "Europe/Chisinau"
  },
  {
    "id": 4367,
    "name": "Glodeni",
    "country_id": 144,
    "country_code": "MD",
    "state_code": "GL",
    "type": "district",
    "latitude": "47.77901560",
    "longitude": "27.51680100",
    "iso3166_2": "MD-GL",
    "native": "Glodeni",
    "timezone": "Europe/Chisinau"
  },
  {
    "id": 4382,
    "name": "Hîncești",
    "country_id": 144,
    "country_code": "MD",
    "state_code": "HI",
    "type": "district",
    "latitude": "46.82811470",
    "longitude": "28.58508890",
    "iso3166_2": "MD-HI",
    "native": "Hîncești",
    "timezone": "Europe/Chisinau"
  },
  {
    "id": 4369,
    "name": "Ialoveni",
    "country_id": 144,
    "country_code": "MD",
    "state_code": "IA",
    "type": "district",
    "latitude": "46.94376000",
    "longitude": "28.77672320",
    "iso3166_2": "MD-IA",
    "native": "Ialoveni",
    "timezone": "Europe/Chisinau"
  },
  {
    "id": 4363,
    "name": "Nisporeni",
    "country_id": 144,
    "country_code": "MD",
    "state_code": "NI",
    "type": "district",
    "latitude": "47.07513490",
    "longitude": "28.17681550",
    "iso3166_2": "MD-NI",
    "native": "Nisporeni",
    "timezone": "Europe/Chisinau"
  },
  {
    "id": 4389,
    "name": "Ocnița",
    "country_id": 144,
    "country_code": "MD",
    "state_code": "OC",
    "type": "district",
    "latitude": "48.41104350",
    "longitude": "27.47680920",
    "iso3166_2": "MD-OC",
    "native": "Ocnița",
    "timezone": "Europe/Chisinau"
  },
  {
    "id": 4361,
    "name": "Orhei",
    "country_id": 144,
    "country_code": "MD",
    "state_code": "OR",
    "type": "district",
    "latitude": "47.38604000",
    "longitude": "28.83030820",
    "iso3166_2": "MD-OR",
    "native": "Orhei",
    "timezone": "Europe/Chisinau"
  },
  {
    "id": 4394,
    "name": "Rezina",
    "country_id": 144,
    "country_code": "MD",
    "state_code": "RE",
    "type": "district",
    "latitude": "47.74892090",
    "longitude": "28.95657390",
    "iso3166_2": "MD-RE",
    "native": "Cauciuc",
    "timezone": "Europe/Chisinau"
  },
  {
    "id": 4376,
    "name": "Rîșcani",
    "country_id": 144,
    "country_code": "MD",
    "state_code": "RI",
    "type": "district",
    "latitude": "47.95359870",
    "longitude": "27.55144530",
    "iso3166_2": "MD-RI",
    "native": "Rîșcani",
    "timezone": "Europe/Chisinau"
  },
  {
    "id": 4364,
    "name": "Sîngerei",
    "country_id": 144,
    "country_code": "MD",
    "state_code": "SI",
    "type": "district",
    "latitude": "47.63891340",
    "longitude": "28.13718160",
    "iso3166_2": "MD-SI",
    "native": "Sîngerei",
    "timezone": "Europe/Chisinau"
  },
  {
    "id": 4388,
    "name": "Șoldănești",
    "country_id": 144,
    "country_code": "MD",
    "state_code": "SD",
    "type": "district",
    "latitude": "47.81473890",
    "longitude": "28.78895860",
    "iso3166_2": "MD-SD",
    "native": "Șoldănești",
    "timezone": "Europe/Chisinau"
  },
  {
    "id": 4374,
    "name": "Soroca",
    "country_id": 144,
    "country_code": "MD",
    "state_code": "SO",
    "type": "district",
    "latitude": "48.15497430",
    "longitude": "28.28707830",
    "iso3166_2": "MD-SO",
    "native": "Soroca",
    "timezone": "Europe/Chisinau"
  },
  {
    "id": 4378,
    "name": "Ștefan Vodă",
    "country_id": 144,
    "country_code": "MD",
    "state_code": "SV",
    "type": "district",
    "latitude": "46.51600240",
    "longitude": "29.66449730",
    "iso3166_2": "MD-SV",
    "native": "Ștefan Vodă",
    "timezone": "Europe/Chisinau"
  },
  {
    "id": 4377,
    "name": "Strășeni",
    "country_id": 144,
    "country_code": "MD",
    "state_code": "ST",
    "type": "district",
    "latitude": "47.14502670",
    "longitude": "28.61367360",
    "iso3166_2": "MD-ST",
    "native": "Strășeni",
    "timezone": "Europe/Chisinau"
  },
  {
    "id": 4372,
    "name": "Taraclia",
    "country_id": 144,
    "country_code": "MD",
    "state_code": "TA",
    "type": "district",
    "latitude": "45.89865100",
    "longitude": "28.66716440",
    "iso3166_2": "MD-TA",
    "native": "Taraclia",
    "timezone": "Europe/Chisinau"
  },
  {
    "id": 4371,
    "name": "Telenești",
    "country_id": 144,
    "country_code": "MD",
    "state_code": "TE",
    "type": "district",
    "latitude": "47.49839620",
    "longitude": "28.36760190",
    "iso3166_2": "MD-TE",
    "native": "Telenești",
    "timezone": "Europe/Chisinau"
  },
  {
    "id": 4395,
    "name": "Transnistria",
    "country_id": 144,
    "country_code": "MD",
    "state_code": "SN",
    "type": "territorial unit",
    "latitude": "47.75986780",
    "longitude": "29.11760550",
    "iso3166_2": "MD-SN",
    "native": "Transnistria",
    "timezone": "Europe/Chisinau"
  },
  {
    "id": 4386,
    "name": "Ungheni",
    "country_id": 144,
    "country_code": "MD",
    "state_code": "UN",
    "type": "district",
    "latitude": "47.20599650",
    "longitude": "27.79891700",
    "iso3166_2": "MD-UN",
    "native": "Ungheni",
    "timezone": "Europe/Chisinau"
  }
]