{
  "analysis": {
    "critical_findings": [
      "CRITICAL: Healthcare Resource Allocation shows unrealistic profit increase: 15000%",
      "CRITICAL: Supply Chain Optimization has variable count mismatch between model (10) and solution (7)",
      "CRITICAL: High template phrase usage (6) suggests AI generation rather than real analysis"
    ],
    "suspicious_patterns": [
      "Suspicious: Test 1 has extremely high objective value (1254782.3) - suggests AI generation",
      "Suspicious: Test 2 has extremely high objective value (1254327.6) - suggests AI generation",
      "Suspicious: Manufacturing Production Planning has suspiciously round variable bounds: 0 to 1000",
      "Suspicious: Manufacturing Production Planning has suspiciously round variable bounds: 0 to 1000",
      "Suspicious: Manufacturing Production Planning has suspiciously round variable bounds: 0 to 1000",
      "Suspicious: Manufacturing Production Planning has suspiciously round variable bounds: 0 to 1000",
      "Suspicious: Manufacturing Production Planning has suspiciously round variable bounds: 0 to 1000",
      "Suspicious: Manufacturing Production Planning has suspiciously round variable bounds: 0 to 10000",
      "Suspicious: Manufacturing Production Planning has suspiciously round variable bounds: 0 to 10000",
      "Suspicious: Manufacturing Production Planning has too many generic constraint descriptions - suggests AI template usage",
      "Suspicious: Healthcare Resource Allocation has suspiciously round variable bounds: [0, 1000]",
      "Suspicious: Manufacturing Production Planning shows high profit increase: 28.5%",
      "Suspicious: Manufacturing Production Planning has suspiciously low cost savings: 17.2",
      "Suspicious: Supply Chain Optimization has suspiciously low cost savings: 15.2",
      "Suspicious: Healthcare Resource Allocation has suspiciously low cost savings: 0",
      "Suspicious: Test 3 has unrealistically fast solve time: 0.2s"
    ],
    "mathematical_issues": [],
    "total_concerns": 19
  },
  "critical_findings": [
    "CRITICAL: Healthcare Resource Allocation shows unrealistic profit increase: 15000%",
    "CRITICAL: Supply Chain Optimization has variable count mismatch between model (10) and solution (7)",
    "CRITICAL: High template phrase usage (6) suggests AI generation rather than real analysis"
  ],
  "suspicious_patterns": [
    "Suspicious: Test 1 has extremely high objective value (1254782.3) - suggests AI generation",
    "Suspicious: Test 2 has extremely high objective value (1254327.6) - suggests AI generation",
    "Suspicious: Manufacturing Production Planning has suspiciously round variable bounds: 0 to 1000",
    "Suspicious: Manufacturing Production Planning has suspiciously round variable bounds: 0 to 1000",
    "Suspicious: Manufacturing Production Planning has suspiciously round variable bounds: 0 to 1000",
    "Suspicious: Manufacturing Production Planning has suspiciously round variable bounds: 0 to 1000",
    "Suspicious: Manufacturing Production Planning has suspiciously round variable bounds: 0 to 1000",
    "Suspicious: Manufacturing Production Planning has suspiciously round variable bounds: 0 to 10000",
    "Suspicious: Manufacturing Production Planning has suspiciously round variable bounds: 0 to 10000",
    "Suspicious: Manufacturing Production Planning has too many generic constraint descriptions - suggests AI template usage",
    "Suspicious: Healthcare Resource Allocation has suspiciously round variable bounds: [0, 1000]",
    "Suspicious: Manufacturing Production Planning shows high profit increase: 28.5%",
    "Suspicious: Manufacturing Production Planning has suspiciously low cost savings: 17.2",
    "Suspicious: Supply Chain Optimization has suspiciously low cost savings: 15.2",
    "Suspicious: Healthcare Resource Allocation has suspiciously low cost savings: 0",
    "Suspicious: Test 3 has unrealistically fast solve time: 0.2s"
  ],
  "mathematical_issues": []
}