[
  {
    "id": 938,
    "name": "Eastern Cape",
    "country_id": 204,
    "country_code": "ZA",
    "state_code": "EC",
    "type": "province",
    "latitude": "-32.21718310",
    "longitude": "26.63864010",
    "iso3166_2": "ZA-EC",
    "native": "Eastern Cape",
    "timezone": "Africa/Johannesburg"
  },
  {
    "id": 932,
    "name": "Free State",
    "country_id": 204,
    "country_code": "ZA",
    "state_code": "FS",
    "type": "province",
    "latitude": "-28.78536180",
    "longitude": "26.49789330",
    "iso3166_2": "ZA-FS",
    "native": "Free State",
    "timezone": "Africa/Johannesburg"
  },
  {
    "id": 936,
    "name": "Gauteng",
    "country_id": 204,
    "country_code": "ZA",
    "state_code": "GP",
    "type": "province",
    "latitude": "-25.93634390",
    "longitude": "28.08131050",
    "iso3166_2": "ZA-GP",
    "native": "Gauteng",
    "timezone": "Africa/Johannesburg"
  },
  {
    "id": 935,
    "name": "KwaZulu-Natal",
    "country_id": 204,
    "country_code": "ZA",
    "state_code": "KZN",
    "type": "province",
    "latitude": "-28.50383300",
    "longitude": "30.88750090",
    "iso3166_2": "ZA-KZN",
    "native": "KwaZulu-Natal",
    "timezone": "Africa/Johannesburg"
  },
  {
    "id": 933,
    "name": "Limpopo",
    "country_id": 204,
    "country_code": "ZA",
    "state_code": "LP",
    "type": "province",
    "latitude": "-23.47352880",
    "longitude": "29.39591990",
    "iso3166_2": "ZA-LP",
    "native": "Limpopo",
    "timezone": "Africa/Johannesburg"
  },
  {
    "id": 937,
    "name": "Mpumalanga",
    "country_id": 204,
    "country_code": "ZA",
    "state_code": "MP",
    "type": "province",
    "latitude": "-26.27684900",
    "longitude": "30.15001530",
    "iso3166_2": "ZA-MP",
    "native": "East",
    "timezone": "Africa/Johannesburg"
  },
  {
    "id": 934,
    "name": "North West",
    "country_id": 204,
    "country_code": "ZA",
    "state_code": "NW",
    "type": "province",
    "latitude": "-26.13478190",
    "longitude": "25.65467290",
    "iso3166_2": "ZA-NW",
    "native": "North West",
    "timezone": "Africa/Johannesburg"
  },
  {
    "id": 931,
    "name": "Northern Cape",
    "country_id": 204,
    "country_code": "ZA",
    "state_code": "NC",
    "type": "province",
    "latitude": "-29.57340200",
    "longitude": "21.20513610",
    "iso3166_2": "ZA-NC",
    "native": "Northern Cape",
    "timezone": "Africa/Johannesburg"
  },
  {
    "id": 939,
    "name": "Western Cape",
    "country_id": 204,
    "country_code": "ZA",
    "state_code": "WC",
    "type": "province",
    "latitude": "-33.54697700",
    "longitude": "20.72753000",
    "iso3166_2": "ZA-WC",
    "native": "Western Cape",
    "timezone": "Africa/Johannesburg"
  }
]