{
  "cpu_version": {
    "index": 1,
    "unit": "",
    "scale": 1,
    "byte": 1,
    "type": "uint8",
    "command": "",
    "valid_min": "",
    "valid_max": "",
    "long_name": "CPU Version",
    "description": "Contains the version number of the CPU firmware."
  },
  "cpu_revision": {
    "index": 2,
    "unit": "",
    "scale": 1,
    "byte": 1,
    "type": "uint8",
    "command": "",
    "valid_min": "",
    "valid_max": "",
    "long_name": "CPU Revision",
    "description": "Contains the revision number of the CPU firmware."
  },
  "system_config_code": {
    "index": 3,
    "unit": "",
    "scale": 1,
    "byte": 2,
    "type": "uint16",
    "command": "",
    "valid_min": "",
    "valid_max": "",
    "long_name": "System Config Code",
    "description": "This field defines the WorkHorse ADCP hardware configuration. Check RDI manual for details."
  },
  "real_flag": {
    "index": 4,
    "unit": "",
    "scale": 1,
    "byte": 1,
    "type": "uint8",
    "command": "PD",
    "valid_min": "",
    "valid_max": "",
    "long_name": "Real Flag",
    "description": "This field is set by default as real data (0)."
  },
  "lag_length": {
    "index": 5,
    "unit": "",
    "scale": 1,
    "byte": 1,
    "type": "uint8",
    "command": "",
    "valid_min": "",
    "valid_max": "",
    "long_name": "Lag Length",
    "description": "The lag length is the time period between sound pulses. This is varied, and therefore of interest in, at a minimum, for the WM5, WM8 and WM11 and BM7 commands."
  },
  "beams": {
    "index": 6,
    "unit": "",
    "scale": 1,
    "byte": 1,
    "type": "uint8",
    "command": "",
    "valid_min": "",
    "valid_max": "",
    "long_name": "Beams",
    "description": "Contains the number of beams used to calculate velocity data (not physical beams). The WorkHorse ADCP needs only three beams to calculate water-current velocities. The fourth beam provides an error velocity that determines data validity. If only three beams are available, the WorkHorse ADCP does not make this validity check."
  },
  "cells": {
    "index": 7,
    "unit": "",
    "scale": 1,
    "byte": 2,
    "type": "uint16",
    "command": "WN",
    "valid_min": "1",
    "valid_max": "255",
    "long_name": "Cells",
    "description": "Contains the number of depth cells over which the WorkHorse ADCP collects data"
  },
  "pings": {
    "index": 8,
    "unit": "",
    "scale": 1,
    "byte": 2,
    "type": "uint16",
    "command": "WP",
    "valid_min": "0",
    "valid_max": "16384",
    "long_name": "Pings",
    "description": "Contains the number of pings averaged together during a data ensemble (WP command). If WP = 0, the WorkHorse ADCP does not collect the WD water-profile data "
  },
  "depth_cell_len": {
    "index": 9,
    "unit": "cm",
    "scale": 1,
    "byte": 2,
    "type": "uint16",
    "command": "WS",
    "valid_min": "1",
    "valid_max": "6400",
    "long_name": "Depth Cell Len",
    "description": "Contains the length of one depth cell"
  },
  "blank_transmit": {
    "index": 10,
    "unit": "cm",
    "scale": 1,
    "byte": 2,
    "type": "uint16",
    "command": "WF",
    "valid_min": "0",
    "valid_max": "9999",
    "long_name": "Blank Transmit",
    "description": "Contains the blanking distance used by the WorkHorse ADCP to allow the transmit circuits time to recover before the receive cycle begins (WF command)."
  },
  "signal_mode": {
    "index": 11,
    "unit": "",
    "scale": 1,
    "byte": 1,
    "type": "uint8",
    "command": "",
    "valid_min": "",
    "valid_max": "",
    "long_name": "Signal Mode",
    "description": "Contains the Signal Processing Mode. This field will always be set to 1."
  },
  "correlation_thresh": {
    "index": 12,
    "unit": "",
    "scale": 1,
    "byte": 1,
    "type": "uint8",
    "command": "WC",
    "valid_min": "0",
    "valid_max": "255",
    "long_name": "Correlation Thresh",
    "description": "Contains the minimum threshold of correlation that water-profile data can have to be considered good data (WC command)"
  },
  "code_reps": {
    "index": 13,
    "unit": "",
    "scale": 1,
    "byte": 1,
    "type": "uint8",
    "command": "",
    "valid_min": "0",
    "valid_max": "255",
    "long_name": "Code Reps",
    "description": "Contains the number of code repetitions in the transmit pulse."
  },
  "percent_good_min": {
    "index": 14,
    "unit": "%",
    "scale": 1,
    "byte": 1,
    "type": "int8",
    "command": "WG",
    "valid_min": "1",
    "valid_max": "100",
    "long_name": "Percent Good Min",
    "description": "Contains the minimum percentage of water-profiling pings in an ensemble that must be considered good to output velocity data."
  },
  "error_velocity_thresh": {
    "index": 15,
    "unit": "mm/s",
    "scale": 1,
    "byte": 2,
    "type": "int16",
    "command": "WE",
    "valid_min": "0",
    "valid_max": "5000",
    "long_name": "Error Velocity Thresh",
    "description": "This field, initially set by the WE command, contains the actual threshold value used to flag water-current data as good or bad. If the error velocity value exceeds this threshold, the WorkHorse ADCP flags all four beams of the affected bin as bad."
  },
  "tp_minute": {
    "index": 16,
    "unit": "",
    "scale": 1,
    "byte": 1,
    "type": "uint8",
    "command": "",
    "valid_min": "",
    "valid_max": "",
    "long_name": "TP Minute",
    "description": "These fields, set by the TP command, contain the amount of time between ping groups in the ensemble. NOTE: The WorkHorse ADCP automatically extends the ensemble interval (set by TE) if (WP x TP > TE)."
  },
  "tp_second": {
    "index": 17,
    "unit": "",
    "scale": 1,
    "byte": 1,
    "type": "uint8",
    "command": "",
    "valid_min": "",
    "valid_max": "",
    "long_name": "TP Second",
    "description": "These fields, set by the TP command, contain the amount of time between ping groups in the ensemble. NOTE: The WorkHorse ADCP automatically extends the ensemble interval (set by TE) if (WP x TP > TE)."
  },
  "tp_hundredth": {
    "index": 18,
    "unit": "",
    "scale": 1,
    "byte": 1,
    "type": "uint8",
    "command": "",
    "valid_min": "",
    "valid_max": "",
    "long_name": "TP Hundredth",
    "description": "Contains the minute portion of the WorkHorse ADCP’s elapsed time measurement of the amount of time needed to complete the pinging of the current ensemble."
  },
  "coord_transform_code": {
    "index": 19,
    "unit": "",
    "scale": "",
    "byte": 1,
    "type": "uint8",
    "command": "EX",
    "valid_min": "",
    "valid_max": "",
    "long_name": "Coord Transform Code",
    "description": "Contains the coordinate transformation processing parameters (EX command). These firmware switches indicate how the WorkHorse ADCP collected data."
  },
  "head_alignment": {
    "index": 20,
    "unit": "degrees",
    "scale": 0.01,
    "byte": 2,
    "type": "uint16",
    "command": "EA",
    "valid_min": "-179.99",
    "valid_max": "180.00",
    "long_name": "Head Alignment",
    "description": "Contains a correction factor for physical heading misalignment."
  },
  "head_bias": {
    "index": 21,
    "unit": "degrees",
    "scale": 0.01,
    "byte": 2,
    "type": "uint16",
    "command": "EB",
    "valid_min": "-179.99",
    "valid_max": "180.00",
    "long_name": "Head Bias",
    "description": "Contains a correction factor for electrical/magnetic heading bias."
  },
  "sensor_source_code": {
    "index": 22,
    "unit": "",
    "scale": "",
    "byte": 1,
    "type": "uint8",
    "command": "EZ",
    "valid_min": "",
    "valid_max": "",
    "long_name": "Sensor Source Code",
    "description": "Contains the selected source of environmental sensor data (EZ command). These firmware switches indicate the following."
  },
  "sensor_avail_code": {
    "index": 23,
    "unit": "",
    "scale": "",
    "byte": 1,
    "type": "uint8",
    "command": "",
    "valid_min": "",
    "valid_max": "",
    "long_name": "Sensor Avail Code",
    "description": "This field reflects which sensors are available"
  },
  "bin_1_dist": {
    "index": 24,
    "unit": "cm",
    "scale": 1,
    "byte": 2,
    "type": "uint16",
    "command": "",
    "valid_min": "0",
    "valid_max": "65535",
    "long_name": "Bin 1 Dist",
    "description": "This field contains the distance to the middle of the first depth cell (bin). This distance is a function of depth cell length (WS), the profiling mode (WM), the blank after transmit distance (WF), and speed of sound."
  },
  "xmit_pulse_len": {
    "index": 25,
    "unit": "cm",
    "scale": 1,
    "byte": 2,
    "type": "uint16",
    "command": "WT",
    "valid_min": "0",
    "valid_max": "65535",
    "long_name": "Xmit Pulse Len",
    "description": "This field, set by the WT command, contains the length of the transmit pulse. When the WorkHorse ADCP receives a <BREAK> signal, it sets the transmit pulse length as close as possible to the depth cell length (WS command). This means the WorkHorse ADCP uses a WT command of zero. However, the WT field contains the actual length of the transmit pulse used."
  },
  "ref_layer_avg": {
    "index": 26,
    "unit": "",
    "scale": 1,
    "byte": 2,
    "type": "uint16",
    "command": "WL",
    "valid_min": "1",
    "valid_max": "128",
    "long_name": "Ref Layer Avg",
    "description": "Contains the starting depth cell (LSB, byte 37) and the ending depth cell (MSB, byte 38) used for water reference layer averaging (WL command)."
  },
  "false_target_thresh": {
    "index": 27,
    "unit": "count",
    "scale": 1,
    "byte": 1,
    "type": "uint8",
    "command": "",
    "valid_min": "0",
    "valid_max": "255",
    "long_name": "False Target Thresh",
    "description": "Contains the threshold value used to reject data received from a false target, usually fish."
  },
  "spare_1": {
    "index": 28,
    "unit": "",
    "scale": 1,
    "byte": 1,
    "type": "uint8",
    "command": "CX",
    "valid_min": "0",
    "valid_max": "5",
    "long_name": "Spare 1",
    "description": "Contains the CX command setting. Range = 0 to 5"
  },
  "transmit_lag_dist": {
    "index": 29,
    "unit": "cm",
    "scale": 1,
    "byte": 2,
    "type": "uint16",
    "command": "WM",
    "valid_min": "0",
    "valid_max": "65535",
    "long_name": "Transmit Lag Dist",
    "description": "These fields contain the outputs of the Analog-to-Digital Converter (ADC) located on the DSP board. The ADC sequentially samples one of the eight channels per ping group (the number of ping groups per ensemble is the maximum of the WP). These fields are zeroed at the beginning of the deployment and updated each ensemble at the rate of one channel per ping group."
  },
  "cpu_serial_no": {
    "index": 30,
    "unit": "",
    "scale": 1,
    "byte": 8,
    "type": "uint64",
    "command": "",
    "valid_min": "",
    "valid_max": "",
    "long_name": "CPU Serial No",
    "description": "Contains the serial number of the CPU board. The CPU Board Serial number is stored in Big Endian (MSB sent first)."
  },
  "system_bandwidth": {
    "index": 31,
    "unit": "",
    "scale": 1,
    "byte": 2,
    "type": "uint16",
    "command": "WB",
    "valid_min": "0",
    "valid_max": "1",
    "long_name": "System Bandwidth",
    "description": "Contains the WB command setting. Range = 0 to 1"
  },
  "system_power": {
    "index": 32,
    "unit": "",
    "scale": 1,
    "byte": 1,
    "type": "uint8",
    "command": "CQ",
    "valid_min": "0",
    "valid_max": "255",
    "long_name": "System Power",
    "description": "Contains the CQ command setting for WorkHorse ADCP Monitor/Sentinel/Long Ranger ADCPs. Range 0 to 255."
  },
  "spare_2": {
    "index": 33,
    "unit": "",
    "scale": 1,
    "byte": 1,
    "type": "uint8",
    "command": "",
    "valid_min": "",
    "valid_max": "",
    "long_name": "Spare 2",
    "description": "Spare"
  },
  "instrument_no": {
    "index": 34,
    "unit": "",
    "scale": "",
    "byte": 4,
    "type": "uint32",
    "command": "CY",
    "valid_min": "",
    "valid_max": "",
    "long_name": "Instrument No",
    "description": "Contains the instrument serial number."
  },
  "beam_angle": {
    "index": 35,
    "unit": "degrees",
    "scale": "",
    "byte": "",
    "type": "uint8",
    "command": "CY",
    "valid_min": "",
    "valid_max": "",
    "long_name": "Beam Angle",
    "description": "Beam Angle"
  }
}
