[
  {
    "id": 48421,
    "name": "Basingstoke",
    "state_id": 2455,
    "state_code": "RDG",
    "country_id": 232,
    "country_code": "GB",
    "latitude": "51.26249000",
    "longitude": "-1.08708000",
    "wikiDataId": null
  },
  {
    "id": 48473,
    "name": "Benson",
    "state_id": 2455,
    "state_code": "RDG",
    "country_id": 232,
    "country_code": "GB",
    "latitude": "51.62073000",
    "longitude": "-1.10979000",
    "wikiDataId": null
  },
  {
    "id": 48658,
    "name": "Bramley",
    "state_id": 2455,
    "state_code": "RDG",
    "country_id": 232,
    "country_code": "GB",
    "latitude": "51.32677000",
    "longitude": "-1.05938000",
    "wikiDataId": null
  },
  {
    "id": 48820,
    "name": "Calcot",
    "state_id": 2455,
    "state_code": "RDG",
    "country_id": 232,
    "country_code": "GB",
    "latitude": "51.44058000",
    "longitude": "-1.05091000",
    "wikiDataId": null
  },
  {
    "id": 48930,
    "name": "Charvil",
    "state_id": 2455,
    "state_code": "RDG",
    "country_id": 232,
    "country_code": "GB",
    "latitude": "51.47573000",
    "longitude": "-0.88591000",
    "wikiDataId": null
  },
  {
    "id": 49904,
    "name": "Henley-on-Thames",
    "state_id": 2455,
    "state_code": "RDG",
    "country_id": 232,
    "country_code": "GB",
    "latitude": "51.53333000",
    "longitude": "-0.90000000",
    "wikiDataId": null
  },
  {
    "id": 50426,
    "name": "Lower Earley",
    "state_id": 2455,
    "state_code": "RDG",
    "country_id": 232,
    "country_code": "GB",
    "latitude": "51.42708000",
    "longitude": "-0.91979000",
    "wikiDataId": null
  },
  {
    "id": 50801,
    "name": "Old Basing",
    "state_id": 2455,
    "state_code": "RDG",
    "country_id": 232,
    "country_code": "GB",
    "latitude": "51.26667000",
    "longitude": "-1.03333000",
    "wikiDataId": null
  },
  {
    "id": 50849,
    "name": "Pangbourne",
    "state_id": 2455,
    "state_code": "RDG",
    "country_id": 232,
    "country_code": "GB",
    "latitude": "51.48370000",
    "longitude": "-1.08519000",
    "wikiDataId": null
  },
  {
    "id": 51045,
    "name": "Reading",
    "state_id": 2455,
    "state_code": "RDG",
    "country_id": 232,
    "country_code": "GB",
    "latitude": "51.45625000",
    "longitude": "-0.97113000",
    "wikiDataId": null
  },
  {
    "id": 51116,
    "name": "Rotherfield Peppard",
    "state_id": 2455,
    "state_code": "RDG",
    "country_id": 232,
    "country_code": "GB",
    "latitude": "51.53064000",
    "longitude": "-0.97847000",
    "wikiDataId": null
  },
  {
    "id": 51266,
    "name": "Sherborne St John",
    "state_id": 2455,
    "state_code": "RDG",
    "country_id": 232,
    "country_code": "GB",
    "latitude": "51.29705000",
    "longitude": "-1.11387000",
    "wikiDataId": null
  },
  {
    "id": 51343,
    "name": "Sonning Common",
    "state_id": 2455,
    "state_code": "RDG",
    "country_id": 232,
    "country_code": "GB",
    "latitude": "51.51873000",
    "longitude": "-0.97753000",
    "wikiDataId": null
  },
  {
    "id": 51489,
    "name": "Stratfield Mortimer",
    "state_id": 2455,
    "state_code": "RDG",
    "country_id": 232,
    "country_code": "GB",
    "latitude": "51.37339000",
    "longitude": "-1.03495000",
    "wikiDataId": null
  },
  {
    "id": 51590,
    "name": "Theale",
    "state_id": 2455,
    "state_code": "RDG",
    "country_id": 232,
    "country_code": "GB",
    "latitude": "51.43694000",
    "longitude": "-1.07700000",
    "wikiDataId": null
  },
  {
    "id": 51733,
    "name": "Wallingford",
    "state_id": 2455,
    "state_code": "RDG",
    "country_id": 232,
    "country_code": "GB",
    "latitude": "51.59982000",
    "longitude": "-1.12480000",
    "wikiDataId": null
  },
  {
    "id": 51750,
    "name": "Wargrave",
    "state_id": 2455,
    "state_code": "RDG",
    "country_id": 232,
    "country_code": "GB",
    "latitude": "51.50068000",
    "longitude": "-0.86577000",
    "wikiDataId": null
  }
]