[
  {
    "id": 48290,
    "name": "Ashford",
    "state_id": 2464,
    "state_code": "KEN",
    "country_id": 232,
    "country_code": "GB",
    "latitude": "51.14648000",
    "longitude": "0.87376000",
    "wikiDataId": null
  },
  {
    "id": 48494,
    "name": "Biddenden",
    "state_id": 2464,
    "state_code": "KEN",
    "country_id": 232,
    "country_code": "GB",
    "latitude": "51.11489000",
    "longitude": "0.63819000",
    "wikiDataId": null
  },
  {
    "id": 48565,
    "name": "Blean",
    "state_id": 2464,
    "state_code": "KEN",
    "country_id": 232,
    "country_code": "GB",
    "latitude": "51.30679000",
    "longitude": "1.04301000",
    "wikiDataId": null
  },
  {
    "id": 48673,
    "name": "Brenchley",
    "state_id": 2464,
    "state_code": "KEN",
    "country_id": 232,
    "country_code": "GB",
    "latitude": "51.15141000",
    "longitude": "0.39825000",
    "wikiDataId": null
  },
  {
    "id": 48922,
    "name": "Charing",
    "state_id": 2464,
    "state_code": "KEN",
    "country_id": 232,
    "country_code": "GB",
    "latitude": "51.21073000",
    "longitude": "0.79466000",
    "wikiDataId": null
  },
  {
    "id": 48929,
    "name": "Chartham",
    "state_id": 2464,
    "state_code": "KEN",
    "country_id": 232,
    "country_code": "GB",
    "latitude": "51.25620000",
    "longitude": "1.01836000",
    "wikiDataId": null
  },
  {
    "id": 49142,
    "name": "Cranbrook",
    "state_id": 2464,
    "state_code": "KEN",
    "country_id": 232,
    "country_code": "GB",
    "latitude": "51.09662000",
    "longitude": "0.53567000",
    "wikiDataId": null
  },
  {
    "id": 49407,
    "name": "East Peckham",
    "state_id": 2464,
    "state_code": "KEN",
    "country_id": 232,
    "country_code": "GB",
    "latitude": "51.21234000",
    "longitude": "0.38624000",
    "wikiDataId": null
  },
  {
    "id": 49535,
    "name": "Faversham",
    "state_id": 2464,
    "state_code": "KEN",
    "country_id": 232,
    "country_code": "GB",
    "latitude": "51.31480000",
    "longitude": "0.88856000",
    "wikiDataId": null
  },
  {
    "id": 49565,
    "name": "Five Oak Green",
    "state_id": 2464,
    "state_code": "KEN",
    "country_id": 232,
    "country_code": "GB",
    "latitude": "51.18338000",
    "longitude": "0.35517000",
    "wikiDataId": null
  },
  {
    "id": 49814,
    "name": "Harrietsham",
    "state_id": 2464,
    "state_code": "KEN",
    "country_id": 232,
    "country_code": "GB",
    "latitude": "51.24252000",
    "longitude": "0.67060000",
    "wikiDataId": null
  },
  {
    "id": 49872,
    "name": "Headcorn",
    "state_id": 2464,
    "state_code": "KEN",
    "country_id": 232,
    "country_code": "GB",
    "latitude": "51.16966000",
    "longitude": "0.62433000",
    "wikiDataId": null
  },
  {
    "id": 49926,
    "name": "High Halden",
    "state_id": 2464,
    "state_code": "KEN",
    "country_id": 232,
    "country_code": "GB",
    "latitude": "51.10331000",
    "longitude": "0.71394000",
    "wikiDataId": null
  },
  {
    "id": 49999,
    "name": "Horsmonden",
    "state_id": 2464,
    "state_code": "KEN",
    "country_id": 232,
    "country_code": "GB",
    "latitude": "51.13908000",
    "longitude": "0.42881000",
    "wikiDataId": null
  },
  {
    "id": 50120,
    "name": "Kennington",
    "state_id": 2464,
    "state_code": "KEN",
    "country_id": 232,
    "country_code": "GB",
    "latitude": "51.16740000",
    "longitude": "0.88491000",
    "wikiDataId": null
  },
  {
    "id": 50123,
    "name": "Kent",
    "state_id": 2464,
    "state_code": "KEN",
    "country_id": 232,
    "country_code": "GB",
    "latitude": "51.16667000",
    "longitude": "0.66667000",
    "wikiDataId": null
  },
  {
    "id": 50279,
    "name": "Lenham",
    "state_id": 2464,
    "state_code": "KEN",
    "country_id": 232,
    "country_code": "GB",
    "latitude": "51.23705000",
    "longitude": "0.71892000",
    "wikiDataId": null
  },
  {
    "id": 50442,
    "name": "Lydd",
    "state_id": 2464,
    "state_code": "KEN",
    "country_id": 232,
    "country_code": "GB",
    "latitude": "50.95132000",
    "longitude": "0.90654000",
    "wikiDataId": null
  },
  {
    "id": 50474,
    "name": "Maidstone",
    "state_id": 2464,
    "state_code": "KEN",
    "country_id": 232,
    "country_code": "GB",
    "latitude": "51.26667000",
    "longitude": "0.51667000",
    "wikiDataId": null
  },
  {
    "id": 50495,
    "name": "Marden",
    "state_id": 2464,
    "state_code": "KEN",
    "country_id": 232,
    "country_code": "GB",
    "latitude": "51.17482000",
    "longitude": "0.48855000",
    "wikiDataId": null
  },
  {
    "id": 50695,
    "name": "New Romney",
    "state_id": 2464,
    "state_code": "KEN",
    "country_id": 232,
    "country_code": "GB",
    "latitude": "50.98599000",
    "longitude": "0.94122000",
    "wikiDataId": null
  },
  {
    "id": 50843,
    "name": "Paddock Wood",
    "state_id": 2464,
    "state_code": "KEN",
    "country_id": 232,
    "country_code": "GB",
    "latitude": "51.18187000",
    "longitude": "0.38229000",
    "wikiDataId": null
  },
  {
    "id": 51102,
    "name": "Romney Marsh",
    "state_id": 2464,
    "state_code": "KEN",
    "country_id": 232,
    "country_code": "GB",
    "latitude": "51.02299000",
    "longitude": "0.91504000",
    "wikiDataId": null
  },
  {
    "id": 51242,
    "name": "Shadoxhurst",
    "state_id": 2464,
    "state_code": "KEN",
    "country_id": 232,
    "country_code": "GB",
    "latitude": "51.10797000",
    "longitude": "0.81917000",
    "wikiDataId": null
  },
  {
    "id": 51316,
    "name": "Sissinghurst",
    "state_id": 2464,
    "state_code": "KEN",
    "country_id": 232,
    "country_code": "GB",
    "latitude": "51.10905000",
    "longitude": "0.56000000",
    "wikiDataId": null
  },
  {
    "id": 51431,
    "name": "Staplehurst",
    "state_id": 2464,
    "state_code": "KEN",
    "country_id": 232,
    "country_code": "GB",
    "latitude": "51.16110000",
    "longitude": "0.55249000",
    "wikiDataId": null
  },
  {
    "id": 51556,
    "name": "Tankerton",
    "state_id": 2464,
    "state_code": "KEN",
    "country_id": 232,
    "country_code": "GB",
    "latitude": "51.36370000",
    "longitude": "1.04913000",
    "wikiDataId": null
  },
  {
    "id": 51577,
    "name": "Tenterden",
    "state_id": 2464,
    "state_code": "KEN",
    "country_id": 232,
    "country_code": "GB",
    "latitude": "51.06845000",
    "longitude": "0.68776000",
    "wikiDataId": null
  },
  {
    "id": 51583,
    "name": "Teynham",
    "state_id": 2464,
    "state_code": "KEN",
    "country_id": 232,
    "country_code": "GB",
    "latitude": "51.33045000",
    "longitude": "0.80526000",
    "wikiDataId": null
  },
  {
    "id": 51880,
    "name": "Whitstable",
    "state_id": 2464,
    "state_code": "KEN",
    "country_id": 232,
    "country_code": "GB",
    "latitude": "51.36070000",
    "longitude": "1.02570000",
    "wikiDataId": null
  },
  {
    "id": 51971,
    "name": "Woodchurch",
    "state_id": 2464,
    "state_code": "KEN",
    "country_id": 232,
    "country_code": "GB",
    "latitude": "51.07605000",
    "longitude": "0.77346000",
    "wikiDataId": null
  },
  {
    "id": 52005,
    "name": "Wye",
    "state_id": 2464,
    "state_code": "KEN",
    "country_id": 232,
    "country_code": "GB",
    "latitude": "51.18249000",
    "longitude": "0.93678000",
    "wikiDataId": null
  },
  {
    "id": 52009,
    "name": "Yalding",
    "state_id": 2464,
    "state_code": "KEN",
    "country_id": 232,
    "country_code": "GB",
    "latitude": "51.22387000",
    "longitude": "0.42920000",
    "wikiDataId": null
  }
]